Workbook

Sheet Resumen
B2: Resumen de Ponderacion y Horas
B4: Curso | C4: 722 - Teoría de Sistemas 1
B5: Semestre que aplica | C5: Segundo Semestre 2026
B6: Total de Puntos del Laboratorio
A8: * Esta sección se auto completa al momento en que se llene a la información de la planificación
A9: ** Tomar como base la distribución realizada por el coordinador del area del curso en el documento de criterios y expectativas
A10: Tipo de Actividad | B10: Ponderacion | C10: Horas utilizadas | D10: Aspectos clave que debe abordar | G10: Valor Maximo Recomendado
A11: Actividades durante el peridodo de laboratorio | B11: =S.2!C7+S.3!C7+S.4!C7+S.5!C7+S.6!C7+S.7!C7+S.8!C7+S.9!C7+S.10!C7+S.11!C7 -> 10 | C11: =5 -> 5 | G11: 10
A12: Proyectos | B12: =Proyectos!C6 -> 60 | C12: =Proyectos!C5 -> 10 | G12: 60
A13: Prácticas | B13: =Practicas!C6 -> 20 | C13: =Practicas!C5 -> 8 | G13: 20
A14: Tareas | B14: =Tareas!C6 -> 10 | C14: =Tareas!C5 -> 14 | G14: 10
A15: Total | B15: =SUM(B11:B14) -> 100 | C15: =SUM(C11:C14) -> 37 | D15: Validacion | E15: =IFERROR(__xludf.DUMMYFUNCTION("LET( nombres,A11:A14, p,B11:B14, m,G11:G14, t,SUM(p), exceden, IFERROR(TEXTJOIN(""; "", TRUE, FILTER(nombres&"" (""&p&"">""&m&"")"", p>m)), """"), negs, IF(COUNTIF(p,""<0"")>0, ""Hay valores negativos"", """"), totalmsg, IF(t<>100, ""Total ≠"&" 100 (actual ""&t&"")"", """"), excesomsg, IF(exceden<>"""", ""Exceden: ""&exceden, """"), msg, TEXTJOIN("" | "", TRUE, totalmsg, negs, excesomsg), IF(msg="""", ""✅ Distribución válida"", ""❌ Revisar: ""&msg) )"),"✅ Distribución válida") -> ✅ Distribución válida

Sheet Competencias
B1: Competencias que se formaran en el Segundo Semestre 2026
B2: Curso | C2: 722 - Teoría de Sistemas 1
B3: Semestre que aplica | C3: Segundo Semestre 2026
B5: Competencias relacionadas al perfil del egresado (Especifica) | I5: Competencias relacionadas al perfil del egresado (General)
B6: 1 | C6: Aplica los conocimientos de su disciplina en la elaboración, fundamentación y defensa de argumentos para prevenir y resolver problemas complejos en su campo profesional, identificando y aplicando innovaciones. | I6: 1 | J6: Aplica principios básicos de ingeniería, ciencias de computación y sistemas de información y comunicación, en la formulación y resolución adecuada de problemas complejos.
B7: 2 | C7: Demuestra pensamiento crítico, actitud investigativa y rigor analítico en el planteamiento y la resolución de problemas complejos. | I7: 2 | J7: Aplica estándares de calidad, eficiencia y seguridad en la implementación adecuada de soluciones de software, hardware y TIC en general.
B8: 3 | C8: Demuestra destreza y habilidad en la selección, uso y adaptación de herramientas metodológicas, tecnológicas, equipos especializados y en la lectura e interpretación de datos, pertinentes al contexto de su ejercicio profesional. | I8: 3
B11: No | C11: Tipo | D11: Verbo en Presente | E11: Objeto de la acción | G11: [Palabras conectoreas] Herramientas o metodología | H11: [Palabras conectoreas] Condiciones específicas | J11: Nivel
B12: 1 | C12: Especifica | D12: Analiza .. | E12: los principios basicos de la teoría de sistemas y su importancia en la vida | G12: mediante modelos sistémicos y recursos gráficos | H12: para analizar el funcionamiento, la estructura y las interacciones de los sistemas en distintos entornos tecnológicos | J12: Analizar
C13: =D12 & " " & E12 & " " &G12& " " &H12& " " -> Analiza .. los principios basicos de la teoría de sistemas y su importancia en la vida mediante modelos sistémicos y recursos gráficos para analizar el funcionamiento, la estructura y las interacciones de los sistemas en distintos entornos tecnológicos
B14: 2 | C14: Especifica | D14: Refina | E14: un problema de ingeniería o un sistema complejo | G14: mediante el uso de Diagramas de Ciclos Causales, Mapas DSRP y metodologías de modelación sistémica | H14: para identificar relaciones causales, retroalimentaciones y estructuras subyacentes que permitan mejorar su comprensión y gestión. | J14: Comprender
C15: =D14 & " " & E14 & " " &G14& " " &H14& " " -> Refina un problema de ingeniería o un sistema complejo mediante el uso de Diagramas de Ciclos Causales, Mapas DSRP y metodologías de modelación sistémica para identificar relaciones causales, retroalimentaciones y estructuras subyacentes que permitan mejorar su comprensión y gestión.
B16: 3 | C16: Especifica | D16: emplea | E16: los principios básicos de la teoría general de sistemas y del enfoque sistémico | G16: el desarrollo de simulaciones dinámicas y la práctica constante de hábitos de pensamiento sistémico | H16: para formular soluciones a problemas de baja y media complejidad | J16: Aplicar
C17: =D16 & " " & E16 & " " &G16& " " &H16& " " -> emplea los principios básicos de la teoría general de sistemas y del enfoque sistémico el desarrollo de simulaciones dinámicas y la práctica constante de hábitos de pensamiento sistémico para formular soluciones a problemas de baja y media complejidad
B18: 4 | C18: Especifica | D18: comprende | E18: los fundamentos conceptuales del pensamiento sistémico y la naturaleza de los sistemas de la realidad | G18: a través del estudio de teorías, modelos mentales y estructuras de retroalimentación | H18: para distinguir los sistemas naturales, físicos diseñados, abstractos diseñados y de actividad humana | J18: Comprender
C19: =D18 & " " & E18 & " " &G18& " " &H18& " " -> comprende los fundamentos conceptuales del pensamiento sistémico y la naturaleza de los sistemas de la realidad a través del estudio de teorías, modelos mentales y estructuras de retroalimentación para distinguir los sistemas naturales, físicos diseñados, abstractos diseñados y de actividad humana
B20: 5 | C20: Especifica | D20: identifica | E20: los conceptos fundamentales de la teoría de sistemas y del pensamiento sistémico | G20: mediante la revisión de definiciones | H20: para reconocer los elementos esenciales en el análisis y modelación de sistemas | J20: Recordar
C21: =D20 & " " & E20 & " " &G20& " " &H20& " " -> identifica los conceptos fundamentales de la teoría de sistemas y del pensamiento sistémico mediante la revisión de definiciones para reconocer los elementos esenciales en el análisis y modelación de sistemas
B22: 6 | C22: Especifica | D22: Diseña | E22: un controlador (ej. PID) o una estrategia de intervención sistémica | G22: para articular las herramientas de modelado y simulación | H22: para combinar las herramientas de modelado y simulación | J22: Crear
C23: =D22 & " " & E22 & " " &G22& " " &H22& " " -> Diseña un controlador (ej. PID) o una estrategia de intervención sistémica para articular las herramientas de modelado y simulación para combinar las herramientas de modelado y simulación
B24: 7 | C24: Especifica | D24: desarrolla | E24: pensamiento sistémico y la construcción de modelos mentales sistémicos | G24: con el fin de comprender, representar | H24: para comprender sistemas complejos en entornos dinámicos y multidisciplinarios | J24: Crear
C25: =D24 & " " & E24 & " " &G24& " " &H24& " " -> desarrolla pensamiento sistémico y la construcción de modelos mentales sistémicos con el fin de comprender, representar para comprender sistemas complejos en entornos dinámicos y multidisciplinarios
B28: Si las competencias son las misma que el semetre anterior compartenos tu opinion de porque no se cambiaron

Sheet Diseño
B2: Diseño de Contenido Curricular
B4: Curso | C4: 722 - Teoría de Sistemas 1
B5: semestre que aplica | C5: Segundo Semestre 2026
B8: No. | C8: Competencia | D8: Nombre de la Unidad | E8: Tema | F8: Subtema | G8: Mes | H8: Semana
B9: 1 | C9: identifica los conceptos fundamentales de la teoría de sistemas y del pensamiento sistémico mediante la revisión de definiciones para reconocer los elementos esenciales en el análisis y modelación de sistemas | D9: Unidad 1: Introducción al pensamiento sistémico | E9: Los modelos mentales o sistemas abstractos diseñados | F9: Pensar en sistemas o pensar de otras maneras | G9: JULIO | H9: 2
B10: 2 | C10: identifica los conceptos fundamentales de la teoría de sistemas y del pensamiento sistémico mediante la revisión de definiciones para reconocer los elementos esenciales en el análisis y modelación de sistemas | D10: Unidad 1: Introducción al pensamiento sistémico | E10: Los modelos mentales o sistemas abstractos diseñados | F10: La realidad interpretada por el pensamiento | G10: JULIO | H10: 2
B11: 3 | C11: identifica los conceptos fundamentales de la teoría de sistemas y del pensamiento sistémico mediante la revisión de definiciones para reconocer los elementos esenciales en el análisis y modelación de sistemas | D11: Unidad 1: Introducción al pensamiento sistémico | E11: Los modelos mentales o sistemas abstractos diseñados | F11: La dinámica de los modelos mentales | G11: JULIO | H11: 2
B12: 4 | C12: identifica los conceptos fundamentales de la teoría de sistemas y del pensamiento sistémico mediante la revisión de definiciones para reconocer los elementos esenciales en el análisis y modelación de sistemas | D12: Unidad 1: Introducción al pensamiento sistémico | E12: Los modelos mentales o sistemas abstractos diseñados | F12: La escalera de inferencias | G12: JULIO | H12: 2
B13: 5 | C13: identifica los conceptos fundamentales de la teoría de sistemas y del pensamiento sistémico mediante la revisión de definiciones para reconocer los elementos esenciales en el análisis y modelación de sistemas | D13: Unidad 1: Introducción al pensamiento sistémico | E13: Los modelos mentales o sistemas abstractos diseñados | F13: Modelos mentales sistémicos | G13: JULIO | H13: 2
B14: 6 | C14: identifica los conceptos fundamentales de la teoría de sistemas y del pensamiento sistémico mediante la revisión de definiciones para reconocer los elementos esenciales en el análisis y modelación de sistemas | D14: Unidad 1: Introducción al pensamiento sistémico | E14: Los modelos mentales o sistemas abstractos diseñados | F14: Comparación de sistemas abstractos | G14: JULIO | H14: 2
B15: 7 | C15: identifica los conceptos fundamentales de la teoría de sistemas y del pensamiento sistémico mediante la revisión de definiciones para reconocer los elementos esenciales en el análisis y modelación de sistemas | D15: Unidad 1: Introducción al pensamiento sistémico | E15: Los modelos mentales o sistemas abstractos diseñados | F15: Operaciones mentales básicas | G15: JULIO | H15: 2
B16: 8 | C16: identifica los conceptos fundamentales de la teoría de sistemas y del pensamiento sistémico mediante la revisión de definiciones para reconocer los elementos esenciales en el análisis y modelación de sistemas | D16: Unidad 2: Los sistemas abstractos diseñados | E16: Operaciones mentales sistémicas | F16: Operaciones mentales básicas del pensamiento sistémico | G16: JULIO | H16: 2
B17: 9 | C17: identifica los conceptos fundamentales de la teoría de sistemas y del pensamiento sistémico mediante la revisión de definiciones para reconocer los elementos esenciales en el análisis y modelación de sistemas | D17: Unidad 2: Los sistemas abstractos diseñados | E17: Operaciones mentales sistémicas | F17: El pensamiento sistémico como emergente | G17: JULIO | H17: 2
B18: 10 | C18: identifica los conceptos fundamentales de la teoría de sistemas y del pensamiento sistémico mediante la revisión de definiciones para reconocer los elementos esenciales en el análisis y modelación de sistemas | D18: Unidad 2: Los sistemas abstractos diseñados | E18: Operaciones mentales sistémicas | F18: Hábitos relacionados con los sistemas abstractos | G18: JULIO | H18: 3
B19: 11 | C19: identifica los conceptos fundamentales de la teoría de sistemas y del pensamiento sistémico mediante la revisión de definiciones para reconocer los elementos esenciales en el análisis y modelación de sistemas | D19: Unidad 2: Los sistemas abstractos diseñados | E19: Operaciones mentales sistémicas | F19: El pensamiento adaptativo complejo | G19: JULIO | H19: 3
B20: 12 | C20: identifica los conceptos fundamentales de la teoría de sistemas y del pensamiento sistémico mediante la revisión de definiciones para reconocer los elementos esenciales en el análisis y modelación de sistemas | D20: Unidad 2: Los sistemas abstractos diseñados | E20: Operaciones mentales sistémicas | F20: La perspectiva en sistemas abstractos | G20: JULIO | H20: 3
... B97: 89 | C97: emplea los principios básicos de la teoría general de sistemas y del enfoque sistémico el desarrollo de simulaciones dinámicas y la práctica constante de hábitos de pensamiento sistémico para formular soluciones a problemas de baja y media complejidad | D97: Unidad 5: Toma de decisiones sistémicas | E97: Toma de decisiones sistémicas | F97: Impacto de la retroalimentación en decisiones | G97: OCTUBRE | H97: 11
B98: 90
B99: 91
B100: 92
B101: 93
B102: 94
B103: 95
B104: 96
B105: 97
B106: 98
B107: 99
B108: 100

Sheet Semana Diagnostico
B2: Diseño de Contenido Curricular
B4: Curso | C4: ='Diseño'!C4 -> 722 - Teoría de Sistemas 1
B5: Semana | C5: 1
B6: Tiempo | C6: =B15+B22+B29+B41+B47+B36 -> 100
K8: Estos puntos son recomendaciones de los puntos a tratar durante tu presentacion, si no usaras estos eres libre de agregar mas filas para indicar que haras. En los recuadros de la derecha colocar breve resumen de lo que planeas decir. No debes ser muy especifico seran pequeñas anotaciones que te ayudaran a recordar lo que planeaste
A9: 1. Bienvenida y Presentación | G9: Tiempo Aproximado | H9: =B15 -> 10
G10: No puedes excederte mas de 15 minutos
A11: Nombre y Formacion Academica | B11: Presentar mi nombre, edad, breve explicacion de mi carrera de sistemas actualmente en el noveno semestre
A12: Experiencia docente y profecional | B12: contar experiencia laboral como desarollador backend
A13: Rol del auxiliar dentro del curso (funciones, actividades y apoyo a los estudiantes). | B13: Indicar apoyo al estudiante por medio de los foros de classroom
A14: Expectativas sobre la dinámica del curso | B14: Participación activa, Pensamiento Crítico y enfoque en apoyo al estudiante
A15: Tiempo que emplearas | B15: 10
A18: 2. Evaluación de Conocimientos Previos | G18: Tiempo Aproximado | H18: =B22 -> 30
G19: No puedes excederte mas de 45 minutos | K19: En los recuadors de la derecha deberas colocar las preguntas que planeas realizar con sus respectivas respuestas. En el segundo recuadro deberas colocar un breve resumne de lo que tines planificado para la parte practica del curso previo al que estas impartiendo.
A20: Redactaras de 15 a 20 preguntas con sus respectivas respuestas , por lo que debes escoge los temas que evaluaras | B20: conceptos basicos sobre teoria de sistemas y pensamiento sistémico
A21: Redactaras una parte practica para realizar la evaluacion de conocimientos previos | B21: Pedir a los estudiantes (ejercicio rápido en el chat/pizarra) que tomen un proceso simple de la vida real (ej. ir al banco, hacer café) y que: 1. Diseñen un Diagrama de Flujo simple que muestre la secuencia de pasos, decisiones y terminación. 2. Identifiquen 3 variables que cambiarían el resultado del proceso (ej. falta de insumos, estado de ánimo).
A22: Tiempo que emplearas | B22: 30
A25: 3. Presentación de los Estudiantes | G25: Tiempo Aproximado | H25: =B29 -> 30
G26: No puedes excederte mas de 30 minutos
A27: Seleccion al Azar de 5 Estudiantes | B27: Utilizaré un generador de números al azar basado en el número de lista de asistencia (ej. un spinner wheel online). | K27: En el primer recuadro colocaras la metodollogia que adoptaras para la eleccion de los estudiantes. En el segundo recuadro colocaras la redaccion de las preguntas que comprendan los siguientes puntos respecto al estudiante: Nombre. Intereses y expectativas sobre el curso. Experiencia previa relacionada con el curso (si aplica). Un dato curioso sobre sí mismo. Consideras que la prueba de conociminetos previos esta acorde al conocimiento que se te brindo en su momento Que tan comodo se sintio con la prueba anterior.
A28: Indica las preguntas que responderan los estudiantes afortunados | B28: 1. Dime tu nombre completo y tu área de interés principal en ingeniería. 2. ¿Qué es lo que más te emociona/esperas aprender en este curso (Pensamiento Sistémico, Modelos Mentales, VENSIM, etc.)? 3. ¿Tienes experiencia previa relacionada con análisis de sistemas o modelado (aunque sea conceptual)?
A29: Tiempo que emplearas | B29: 30
A32: 4. Senso de Horarios de Calificación | G32: Tiempo Aproximado | H32: =B36 -> 10
A33: Deberas estar recordando que deben contestar el formulario asi mismo dejar el link fijado en la llamada | G33: Esta actividad quedara abierta hasta el fin de la clase. pero emplearas 5 min especificos para la actividad
A34: Link de google forms donde este el cuestionario | K34: Esta actividad te ayudara a realizar un senso de posibles horarios de calificacion y que tus estudiantes esten enterados y puedan preveer los dias de calificacion y asi mismo el horario. Deberas colocar en los reacuadros de la derecha link de Google form libre para correos intitucionales, esto para garantizar una sola respuesta por estudiante. TAmbien deberas colocar los posibles horarios y dias que tentativamente tendrias disponibles. para colocarlos en el google form.
A35: Dias y posibles Horarios de calificacion | B35: Sabados a partir de 10 AM
A36: Tiempo que emplearas | B36: 10
A39: 5. Mostrar Programa del Curso | G39: Tiempo Aproximado | H39: =B41 -> 10
G40: No puedes excederte mas de 30 minutos
A41: Tiempo que emplearas | B41: 10
A44: 6. Evaluación de Conocimientos del Curso Actual | G44: Tiempo Aproximado | H44: =B47 -> 10
G45: No puedes excederte mas de 15 minutos
A46: Redactaras 20 preguntas con sus respectivas respuestas | B46: Preguntas y Respuestas (20 preguntas, 15 min): (Ejemplos que miden interés y expectativa sobre el contenido que acabas de presentar y que verán) 1. ¿Qué es la Escalera de Inferencias? (R: Proceso mental que lleva de datos a creencias/acciones). 2. Mencione una Operación Mental Sistémica. (R: Distinción, Relación, Perspectiva, Organización). 3. ¿Cuál es el objetivo principal del Modelo del Iceberg? (R: Buscar causas estructurales, no solo eventos). 4. ¿Qué representan las flechas en un Diagrama de Ciclos Causales (DCC)? (R: Relaciones de causalidad). 5. Defina Retroalimentación de Refuerzo (R). (R: Mecanismo que amplifica el cambio o causa crecimiento/declive exponencial). 6. Mencione el software que usaremos para simulación dinámica. (R: VENSIM). 7. ¿Qué es un Arquetipo Sistémico? (R: Estructura de DCC recurrente que causa problemas comunes). 8. ¿Cuál es la diferencia entre un Bucle R y uno C en la dinámica? (R: R genera crecimiento/declive; C genera equilibrio/estabilidad). 9. ¿Qué significa Alto Apalancamiento en intervención? (R: Un pequeño cambio estructural que genera gran impacto en el sistema). 10. ¿En qué unidad se enfoca el curso en la Toma de Decisiones Estratégicas? (R: Unidad 5).
A47: Tiempo que emplearas | B47: 10

Sheet S.2
B2: Diseño de la Sesión de Laboratorio
B4: Curso | C4: ='Diseño'!C4 -> 722 - Teoría de Sistemas 1
B5: Semana | C5: 2
B6: Tiempo | C6: =H10+H21+H44+H68 -> 100
B7: Ponderación | C7: =B49+B60 -> 1
B8: Validación de Tiempo | C8: =IF(H44<=0, "❌ ERROR: La Actividad 1 debe tener un tiempo mayor a 0.", IF(H21>60, "❌ ERROR: El 'Área de Conocimiento' no puede exceder los 60 min.", IF((H10+H21+H44)<100, "❌ ERROR: El tiempo total debe ser de al menos 100 min.", "✅ VALIDACIÓN CORRECTA"))) -> ❌ ERROR: El tiempo total debe ser de al menos 100 min.
A10: 1. Área Actitudinal (Saber Ser) | G10: Tiempo Aproximado | H10: =B13 -> 5
G11: Tiene que estar en un rango de 3 a 5 minutos
A12: Nombre del Valor | B12: Apertura mental
A13: Tiempo Aproximado | B13: 5
A14: Descripcion
A15: Disposición a cuestionar las propias suposiciones y reconocer que la "realidad" es subjetivamente interpretada por filtros mentales.
A17: Como se relaciona con los conocimientos de la sesion y se aplicaria
A18: La sesión se centra en la Escalera de Inferencias. Aplicar la Apertura Mental permite al estudiante identificar sus propios juicios y sesgos, mejorando la calidad de su análisis antes de formular modelos.
A21: 2. Área Conocimiento (Saber) | G21: Tiempo Aproximado | H21: =SUM(D39:H42) -> 45
G22: No puede exceder los 60 minutos
A23: Competencia a desarrollar | B23: identifica los conceptos fundamentales de la teoría de sistemas y del pensamiento sistémico mediante la revisión de definiciones para reconocer los elementos esenciales en el análisis y modelación de sistemas
A24: Competencia a desarrollar
A26: 2.1 Contenido
A27: No. | B27: Unidad | D27: Tema | F27: Sub Tema
A28: 1 | B28: =IFERROR(__xludf.DUMMYFUNCTION("FILTER('Diseño'!D:D,'Diseño'!H:H=$C$5)"),"Unidad 1: Introducción al pensamiento sistémico") -> Unidad 1: Introducción al pensamiento sistémico | D28: =IFERROR(__xludf.DUMMYFUNCTION("FILTER('Diseño'!E:E,'Diseño'!H:H=$C$5)"),"Los modelos mentales o sistemas abstractos diseñados") -> Los modelos mentales o sistemas abstractos diseñados | F28: =IFERROR(__xludf.DUMMYFUNCTION("FILTER('Diseño'!F:F,'Diseño'!H:H=$C$5)"),"Pensar en sistemas o pensar de otras maneras") -> Pensar en sistemas o pensar de otras maneras
A29: 2 | B29: =IFERROR(__xludf.DUMMYFUNCTION("""COMPUTED_VALUE"""),"Unidad 1: Introducción al pensamiento sistémico") -> Unidad 1: Introducción al pensamiento sistémico | D29: =IFERROR(__xludf.DUMMYFUNCTION("""COMPUTED_VALUE"""),"Los modelos mentales o sistemas abstractos diseñados") -> Los modelos mentales o sistemas abstractos diseñados | F29: =IFERROR(__xludf.DUMMYFUNCTION("""COMPUTED_VALUE"""),"La realidad interpretada por el pensamiento") -> La realidad interpretada por el pensamiento
A30: 3 | B30: =IFERROR(__xludf.DUMMYFUNCTION("""COMPUTED_VALUE"""),"Unidad 1: Introducción al pensamiento sistémico") -> Unidad 1: Introducción al pensamiento sistémico | D30: =IFERROR(__xludf.DUMMYFUNCTION("""COMPUTED_VALUE"""),"Los modelos mentales o sistemas abstractos diseñados") -> Los modelos mentales o sistemas abstractos diseñados | F30: =IFERROR(__xludf.DUMMYFUNCTION("""COMPUTED_VALUE"""),"La dinámica de los modelos mentales") -> La dinámica de los modelos mentales
A31: 4 | B31: =IFERROR(__xludf.DUMMYFUNCTION("""COMPUTED_VALUE"""),"Unidad 1: Introducción al pensamiento sistémico") -> Unidad 1: Introducción al pensamiento sistémico | D31: =IFERROR(__xludf.DUMMYFUNCTION("""COMPUTED_VALUE"""),"Los modelos mentales o sistemas abstractos diseñados") -> Los modelos mentales o sistemas abstractos diseñados | F31: =IFERROR(__xludf.DUMMYFUNCTION("""COMPUTED_VALUE"""),"La escalera de inferencias") -> La escalera de inferencias
A32: 5 | B32: =IFERROR(__xludf.DUMMYFUNCTION("""COMPUTED_VALUE"""),"Unidad 1: Introducción al pensamiento sistémico") -> Unidad 1: Introducción al pensamiento sistémico | D32: =IFERROR(__xludf.DUMMYFUNCTION("""COMPUTED_VALUE"""),"Los modelos mentales o sistemas abstractos diseñados") -> Los modelos mentales o sistemas abstractos diseñados | F32: =IFERROR(__xludf.DUMMYFUNCTION("""COMPUTED_VALUE"""),"Modelos mentales sistémicos") -> Modelos mentales sistémicos
A33: 6 | B33: =IFERROR(__xludf.DUMMYFUNCTION("""COMPUTED_VALUE"""),"Unidad 1: Introducción al pensamiento sistémico") -> Unidad 1: Introducción al pensamiento sistémico | D33: =IFERROR(__xludf.DUMMYFUNCTION("""COMPUTED_VALUE"""),"Los modelos mentales o sistemas abstractos diseñados") -> Los modelos mentales o sistemas abstractos diseñados | F33: =IFERROR(__xludf.DUMMYFUNCTION("""COMPUTED_VALUE"""),"Comparación de sistemas abstractos") -> Comparación de sistemas abstractos
A34: 7 | B34: =IFERROR(__xludf.DUMMYFUNCTION("""COMPUTED_VALUE"""),"Unidad 1: Introducción al pensamiento sistémico") -> Unidad 1: Introducción al pensamiento sistémico | D34: =IFERROR(__xludf.DUMMYFUNCTION("""COMPUTED_VALUE"""),"Los modelos mentales o sistemas abstractos diseñados") -> Los modelos mentales o sistemas abstractos diseñados | F34: =IFERROR(__xludf.DUMMYFUNCTION("""COMPUTED_VALUE"""),"Operaciones mentales básicas") -> Operaciones mentales básicas
B35: =IFERROR(__xludf.DUMMYFUNCTION("""COMPUTED_VALUE"""),"Unidad 2: Los sistemas abstractos diseñados") -> Unidad 2: Los sistemas abstractos diseñados | D35: =IFERROR(__xludf.DUMMYFUNCTION("""COMPUTED_VALUE"""),"Operaciones mentales sistémicas") -> Operaciones mentales sistémicas | F35: =IFERROR(__xludf.DUMMYFUNCTION("""COMPUTED_VALUE"""),"Operaciones mentales básicas del pensamiento sistémico") -> Operaciones mentales básicas del pensamiento sistémico
A36: 2.2 Recursos Educativos | B36: =IFERROR(__xludf.DUMMYFUNCTION("""COMPUTED_VALUE"""),"Unidad 2: Los sistemas abstractos diseñados") -> Unidad 2: Los sistemas abstractos diseñados | D36: =IFERROR(__xludf.DUMMYFUNCTION("""COMPUTED_VALUE"""),"Operaciones mentales sistémicas") -> Operaciones mentales sistémicas | F36: =IFERROR(__xludf.DUMMYFUNCTION("""COMPUTED_VALUE"""),"El pensamiento sistémico como emergente") -> El pensamiento sistémico como emergente
A38: Tipo de Recurso a utilizar | B38: Tipo | C38: Valor maximo recomendado en Minutos | D38: Tiempo Aproximado ( unicamente el valor de minutos ) | I38: Validacion
A39: Presentacion | B39: Obligatorio | C39: 30 | D39: 25 | I39: =IF(D39<=C39,"Correcto", "Corregir") -> Correcto
A40: Video | B40: Obligatorio | C40: 6 | D40: 5 | I40: =IF(D40<=C40,"Correcto", "Corregir") -> Correcto
A41: Lectura | B41: Optativo | C41: 10 | D41: 5 | I41: =IF(D41<=C41,"Correcto", "Corregir") -> Correcto
A42: Ejercicio Demostrativo | B42: Obligatorio | C42: 30 | D42: 10 | I42: =IF(D42<=C42,"Correcto", "Corregir") -> Correcto
A44: 3. Área de Habilidades (Saber Hacer) | G44: Tiempo Aproximado | H44: =B50 -> 40
G45: Tiene que estar en un rango de 30 a 50 minutos
A46: Actividad 1 (Obligatoria)
A47: Competencia que predomina en la actividad | B47: Refina un problema de ingeniería o un sistema complejo mediante el uso de Diagramas de Ciclos Causales, Mapas DSRP y metodologías de modelación sistémica para identificar relaciones causales, retroalimentaciones y estructuras subyacentes que permitan mejorar su comprensión y gestión.
A48: Tipo de Actividad | B48: Analisis
A49: Ponderación | B49: 1
A50: Tiempo Aproximado | B50: 40
A51: Coloca el tiempo que usar en la actividad, un tiempo sugerido 30 minutos
A52: Descripcion de la Actividad
A53: Los estudiantes trabajan en parejas con un caso ambiguo donde una persona salta a una conclusión rápidamente (ej. "Mi jefe no confía en mí porque no me invitó a la reunión").
A57: Actividad 2 (Optativa puedes hacerla si lo consideras apropiado)
A58: Competencia que predomina en la actividad
A59: Tipo de Actividad
A60: Ponderación
A61: Tiempo Aproximado
A62: Coloca el tiempo que usar en la actividad, un tiempo sugerido 20 minutos
A63: Descripcion de la Actividad
A64: Se pide a los estudiantes que piensen en un sistema de ingeniería conocido (ej. un termostato de casa o el control de velocidad de un carro).
A68: 3. Cierre | G68: Tiempo Aproximado | H68: =B70 -> 10
G69: Tiene que estar en un rango de 10 a 15 minutos
A70: Tiempo Aproximado | B70: 10
A71: Asignacion de Actividades
A72: 1. Conclusión (3 min): La calidad del modelo de ingeniería comienza con la calidad del modelo mental (la interpretación de la realidad). 2. Asignación de Actividades (7 min): Tarea Preparatoria Obligatoria (para Semana 3): Investigar a fondo las Operaciones Mentales Básicas del Pensamiento Sistémico (Distinción, Relación, Perspectiva, Organización) y la definición de Pensamiento Adaptativo Complejo.
A74: Resuelve alguna duda, asigna las actividades que deben realizar, dudas de proyectos, etc

Sheet S.3
B2: Diseño de la Sesión de Laboratorio
B4: Curso | C4: ='Diseño'!C4 -> 722 - Teoría de Sistemas 1
B5: Semana | C5: 3
B6: Tiempo | C6: =H10+H21+H44+H68 -> 100
B7: Ponderación | C7: =B49+B60 -> 1
B8: Validación de Tiempo | C8: =IF(H44<=0, "❌ ERROR: La Actividad 1 debe tener un tiempo mayor a 0.", IF(H21>60, "❌ ERROR: El 'Área de Conocimiento' no puede exceder los 60 min.", IF((H10+H21+H44)<100, "❌ ERROR: El tiempo total debe ser de al menos 100 min.", "✅ VALIDACIÓN CORRECTA"))) -> ❌ ERROR: El tiempo total debe ser de al menos 100 min.
A10: 1. Área Actitudinal (Saber Ser) | G10: Tiempo Aproximado | H10: =B13 -> 5
G11: Tiene que estar en un rango de 3 a 5 minutos
A12: Nombre del Valor | B12: Conciencia Sistémica
A13: Tiempo Aproximado | B13: 5
A14: Descripcion
A15: Reconocer que las soluciones eficaces se encuentran en el cambio de estructura y perspectiva (el sistema), no solo de los componentes.
A17: Como se relaciona con los conocimientos de la sesion y se aplicaria
A18: Se relaciona con el Pensamiento Sistémico como Emergente y la Perspectiva. Fomenta la habilidad de Comprender que los problemas complejos requieren cambiar el marco mental (paradigma), un paso esencial antes de aplicar soluciones técnicas.
A21: 2. Área Conocimiento (Saber) | G21: Tiempo Aproximado | H21: =SUM(D39:H42) -> 50
G22: No puede exceder los 60 minutos
A23: Competencia a desarrollar | B23: comprende los fundamentos conceptuales del pensamiento sistémico y la naturaleza de los sistemas de la realidad a través del estudio de teorías, modelos mentales y estructuras de retroalimentación para distinguir los sistemas naturales, físicos diseñados, abstractos diseñados y de actividad humana
A24: Competencia a desarrollar
A26: 2.1 Contenido
A27: No. | B27: Unidad | D27: Tema | F27: Sub Tema
A28: 1 | B28: =IFERROR(__xludf.DUMMYFUNCTION("FILTER('Diseño'!D:D,'Diseño'!H:H=$C$5)"),"Unidad 2: Los sistemas abstractos diseñados") -> Unidad 2: Los sistemas abstractos diseñados | D28: =IFERROR(__xludf.DUMMYFUNCTION("FILTER('Diseño'!E:E,'Diseño'!H:H=$C$5)"),"Operaciones mentales sistémicas") -> Operaciones mentales sistémicas | F28: =IFERROR(__xludf.DUMMYFUNCTION("FILTER('Diseño'!F:F,'Diseño'!H:H=$C$5)"),"Hábitos relacionados con los sistemas abstractos") -> Hábitos relacionados con los sistemas abstractos
A29: 2 | B29: =IFERROR(__xludf.DUMMYFUNCTION("""COMPUTED_VALUE"""),"Unidad 2: Los sistemas abstractos diseñados") -> Unidad 2: Los sistemas abstractos diseñados | D29: =IFERROR(__xludf.DUMMYFUNCTION("""COMPUTED_VALUE"""),"Operaciones mentales sistémicas") -> Operaciones mentales sistémicas | F29: =IFERROR(__xludf.DUMMYFUNCTION("""COMPUTED_VALUE"""),"El pensamiento adaptativo complejo") -> El pensamiento adaptativo complejo
A30: 3 | B30: =IFERROR(__xludf.DUMMYFUNCTION("""COMPUTED_VALUE"""),"Unidad 2: Los sistemas abstractos diseñados") -> Unidad 2: Los sistemas abstractos diseñados | D30: =IFERROR(__xludf.DUMMYFUNCTION("""COMPUTED_VALUE"""),"Operaciones mentales sistémicas") -> Operaciones mentales sistémicas | F30: =IFERROR(__xludf.DUMMYFUNCTION("""COMPUTED_VALUE"""),"La perspectiva en sistemas abstractos") -> La perspectiva en sistemas abstractos
A31: 4 | B31: =IFERROR(__xludf.DUMMYFUNCTION("""COMPUTED_VALUE"""),"Unidad 2: Los sistemas abstractos diseñados") -> Unidad 2: Los sistemas abstractos diseñados | D31: =IFERROR(__xludf.DUMMYFUNCTION("""COMPUTED_VALUE"""),"Operaciones mentales sistémicas") -> Operaciones mentales sistémicas | F31: =IFERROR(__xludf.DUMMYFUNCTION("""COMPUTED_VALUE"""),"Comparación entre sistemas diseñados") -> Comparación entre sistemas diseñados
A32: 5 | B32: =IFERROR(__xludf.DUMMYFUNCTION("""COMPUTED_VALUE"""),"Unidad 2: Los sistemas abstractos diseñados") -> Unidad 2: Los sistemas abstractos diseñados | D32: =IFERROR(__xludf.DUMMYFUNCTION("""COMPUTED_VALUE"""),"Operaciones mentales sistémicas") -> Operaciones mentales sistémicas | F32: =IFERROR(__xludf.DUMMYFUNCTION("""COMPUTED_VALUE"""),"Ejemplos de sistemas mentales") -> Ejemplos de sistemas mentales
A33: 6 | B33: =IFERROR(__xludf.DUMMYFUNCTION("""COMPUTED_VALUE"""),"Unidad 2: Los sistemas abstractos diseñados") -> Unidad 2: Los sistemas abstractos diseñados | D33: =IFERROR(__xludf.DUMMYFUNCTION("""COMPUTED_VALUE"""),"Compartir modelos mentales") -> Compartir modelos mentales | F33: =IFERROR(__xludf.DUMMYFUNCTION("""COMPUTED_VALUE"""),"Sistemas abstractos diseñados compartidos (paradigmas)") -> Sistemas abstractos diseñados compartidos (paradigmas)
A34: 7 | B34: =IFERROR(__xludf.DUMMYFUNCTION("""COMPUTED_VALUE"""),"Unidad 2: Los sistemas abstractos diseñados") -> Unidad 2: Los sistemas abstractos diseñados | D34: =IFERROR(__xludf.DUMMYFUNCTION("""COMPUTED_VALUE"""),"Compartir modelos mentales") -> Compartir modelos mentales | F34: =IFERROR(__xludf.DUMMYFUNCTION("""COMPUTED_VALUE"""),"Paradigmas en contextos específicos") -> Paradigmas en contextos específicos
B35: =IFERROR(__xludf.DUMMYFUNCTION("""COMPUTED_VALUE"""),"Unidad 2: Los sistemas abstractos diseñados") -> Unidad 2: Los sistemas abstractos diseñados | D35: =IFERROR(__xludf.DUMMYFUNCTION("""COMPUTED_VALUE"""),"Compartir modelos mentales") -> Compartir modelos mentales | F35: =IFERROR(__xludf.DUMMYFUNCTION("""COMPUTED_VALUE"""),"Comparación con otros paradigmas") -> Comparación con otros paradigmas
A36: 2.2 Recursos Educativos | B36: =IFERROR(__xludf.DUMMYFUNCTION("""COMPUTED_VALUE"""),"Unidad 2: Los sistemas abstractos diseñados") -> Unidad 2: Los sistemas abstractos diseñados | D36: =IFERROR(__xludf.DUMMYFUNCTION("""COMPUTED_VALUE"""),"Compartir modelos mentales") -> Compartir modelos mentales | F36: =IFERROR(__xludf.DUMMYFUNCTION("""COMPUTED_VALUE"""),"Ejemplos de paradigmas compartidos") -> Ejemplos de paradigmas compartidos
A38: Tipo de Recurso a utilizar | B38: Tipo | C38: Valor maximo recomendado en Minutos | D38: Tiempo Aproximado ( unicamente el valor de minutos ) | I38: Validacion
A39: Presentacion | B39: Obligatorio | C39: 30 | D39: 20 | I39: =IF(D39<=C39,"Correcto", "Corregir") -> Correcto
A40: Video | B40: Obligatorio | C40: 6 | D40: 5 | I40: =IF(D40<=C40,"Correcto", "Corregir") -> Correcto
A41: Lectura | B41: Optativo | C41: 10 | D41: 5 | I41: =IF(D41<=C41,"Correcto", "Corregir") -> Correcto
A42: Ejercicio Demostrativo | B42: Obligatorio | C42: 30 | D42: 20 | I42: =IF(D42<=C42,"Correcto", "Corregir") -> Correcto
A44: 3. Área de Habilidades (Saber Hacer) | G44: Tiempo Aproximado | H44: =B50 -> 35
G45: Tiene que estar en un rango de 30 a 50 minutos
A46: Actividad 1 (Obligatoria)
A47: Competencia que predomina en la actividad | B47: comprende los fundamentos conceptuales del pensamiento sistémico y la naturaleza de los sistemas de la realidad a través del estudio de teorías, modelos mentales y estructuras de retroalimentación para distinguir los sistemas naturales, físicos diseñados, abstractos diseñados y de actividad humana
A48: Tipo de Actividad | B48: otros
A49: Ponderación | B49: 1
A50: Tiempo Aproximado | B50: 35
A51: Coloca el tiempo que usar en la actividad, un tiempo sugerido 30 minutos
A52: Descripcion de la Actividad
A53: Los estudiantes reciben un Paradigma conocido (ej. "Siempre hay que maximizar la eficiencia y reducir costos al máximo"). Deben Comprender cómo este paradigma (modelo mental compartido) impacta negativamente en el sistema completo a largo plazo (ej. afecta la calidad, la moral, o la innovación). Discutir si es un ejemplo de pensamiento adaptativo complejo o una trampa mental.
A57: Actividad 2 (Optativa puedes hacerla si lo consideras apropiado)
A58: Competencia que predomina en la actividad
A59: Tipo de Actividad
A60: Ponderación
A61: Tiempo Aproximado
A62: Coloca el tiempo que usar en la actividad, un tiempo sugerido 20 minutos
A63: Descripcion de la Actividad
A68: 3. Cierre | G68: Tiempo Aproximado | H68: =B70 -> 10
G69: Tiene que estar en un rango de 10 a 15 minutos
A70: Tiempo Aproximado | B70: 10
A71: Asignacion de Actividades
A72: Lectura Optativa: Tutorial introductorio sobre el manejo de MATLAB/SIMULINK (preparación para el uso de la herramienta referente del MIT en la semana 7).
A74: Resuelve alguna duda, asigna las actividades que deben realizar, dudas de proyectos, etc

Sheet S.4
B2: Diseño de la Sesión de Laboratorio
B4: Curso | C4: ='Diseño'!C4 -> 722 - Teoría de Sistemas 1
B5: Semana | C5: 4
B6: Tiempo | C6: =H10+H21+H44+H68 -> 100
B7: Ponderación | C7: =B49+B60 -> 1
B8: Validación de Tiempo | C8: =IF(H44<=0, "❌ ERROR: La Actividad 1 debe tener un tiempo mayor a 0.", IF(H21>60, "❌ ERROR: El 'Área de Conocimiento' no puede exceder los 60 min.", IF((H10+H21+H44)<100, "❌ ERROR: El tiempo total debe ser de al menos 100 min.", "✅ VALIDACIÓN CORRECTA"))) -> ❌ ERROR: El tiempo total debe ser de al menos 100 min.
A10: 1. Área Actitudinal (Saber Ser) | G10: Tiempo Aproximado | H10: =B13 -> 5
G11: Tiene que estar en un rango de 3 a 5 minutos
A12: Nombre del Valor | B12: Orientación a la Causa Raíz
A13: Tiempo Aproximado | B13: 5
A14: Descripcion
A15: Enfocarse en la estructura del sistema (el círculo) en lugar de los eventos (la línea) para evitar la transferencia del problema.
A17: Como se relaciona con los conocimientos de la sesion y se aplicaria
A18: Se relaciona con los Ejemplos de Retroalimentación y Pensamiento Circular. Fomenta la habilidad de Comprender y aplicar la lógica sistémica, alejándose de la búsqueda de una única "causa" lineal.
A21: 2. Área Conocimiento (Saber) | G21: Tiempo Aproximado | H21: =SUM(D39:H42) -> 40
G22: No puede exceder los 60 minutos
A23: Competencia a desarrollar | B23: comprende los fundamentos conceptuales del pensamiento sistémico y la naturaleza de los sistemas de la realidad a través del estudio de teorías, modelos mentales y estructuras de retroalimentación para distinguir los sistemas naturales, físicos diseñados, abstractos diseñados y de actividad humana
A24: Competencia a desarrollar
A26: 2.1 Contenido
A27: No. | B27: Unidad | D27: Tema | F27: Sub Tema
A28: 1 | B28: =IFERROR(__xludf.DUMMYFUNCTION("FILTER('Diseño'!D:D,'Diseño'!H:H=$C$5)"),"Unidad 2: Los sistemas abstractos diseñados") -> Unidad 2: Los sistemas abstractos diseñados | D28: =IFERROR(__xludf.DUMMYFUNCTION("FILTER('Diseño'!E:E,'Diseño'!H:H=$C$5)"),"Compartir modelos mentales") -> Compartir modelos mentales | F28: =IFERROR(__xludf.DUMMYFUNCTION("FILTER('Diseño'!F:F,'Diseño'!H:H=$C$5)"),"Impacto en toma de decisiones") -> Impacto en toma de decisiones
A29: 2 | B29: =IFERROR(__xludf.DUMMYFUNCTION("""COMPUTED_VALUE"""),"Unidad 2: Los sistemas abstractos diseñados") -> Unidad 2: Los sistemas abstractos diseñados | D29: =IFERROR(__xludf.DUMMYFUNCTION("""COMPUTED_VALUE"""),"Compartir modelos mentales") -> Compartir modelos mentales | F29: =IFERROR(__xludf.DUMMYFUNCTION("""COMPUTED_VALUE"""),"Evolución de paradigmas") -> Evolución de paradigmas
A30: 3 | B30: =IFERROR(__xludf.DUMMYFUNCTION("""COMPUTED_VALUE"""),"Unidad 2: Los sistemas abstractos diseñados") -> Unidad 2: Los sistemas abstractos diseñados | D30: =IFERROR(__xludf.DUMMYFUNCTION("""COMPUTED_VALUE"""),"Compartir modelos mentales") -> Compartir modelos mentales | F30: =IFERROR(__xludf.DUMMYFUNCTION("""COMPUTED_VALUE"""),"Cambios en modelos mentales compartidos") -> Cambios en modelos mentales compartidos
A31: 4 | B31: =IFERROR(__xludf.DUMMYFUNCTION("""COMPUTED_VALUE"""),"Unidad 2: Los sistemas abstractos diseñados") -> Unidad 2: Los sistemas abstractos diseñados | D31: =IFERROR(__xludf.DUMMYFUNCTION("""COMPUTED_VALUE"""),"Perspectiva de sistemas abstractos diseñados") -> Perspectiva de sistemas abstractos diseñados | F31: =IFERROR(__xludf.DUMMYFUNCTION("""COMPUTED_VALUE"""),"Las perspectivas y los sistemas abstractos") -> Las perspectivas y los sistemas abstractos
A32: 5 | B32: =IFERROR(__xludf.DUMMYFUNCTION("""COMPUTED_VALUE"""),"Unidad 2: Los sistemas abstractos diseñados") -> Unidad 2: Los sistemas abstractos diseñados | D32: =IFERROR(__xludf.DUMMYFUNCTION("""COMPUTED_VALUE"""),"Perspectiva de sistemas abstractos diseñados") -> Perspectiva de sistemas abstractos diseñados | F32: =IFERROR(__xludf.DUMMYFUNCTION("""COMPUTED_VALUE"""),"Impacto de las perspectivas en decisiones") -> Impacto de las perspectivas en decisiones
A33: 6 | B33: =IFERROR(__xludf.DUMMYFUNCTION("""COMPUTED_VALUE"""),"Unidad 2: Los sistemas abstractos diseñados") -> Unidad 2: Los sistemas abstractos diseñados | D33: =IFERROR(__xludf.DUMMYFUNCTION("""COMPUTED_VALUE"""),"Perspectiva de sistemas abstractos diseñados") -> Perspectiva de sistemas abstractos diseñados | F33: =IFERROR(__xludf.DUMMYFUNCTION("""COMPUTED_VALUE"""),"Operaciones mentales avanzadas en pensamiento sistémico") -> Operaciones mentales avanzadas en pensamiento sistémico
A34: 7 | B34: =IFERROR(__xludf.DUMMYFUNCTION("""COMPUTED_VALUE"""),"Unidad 2: Los sistemas abstractos diseñados") -> Unidad 2: Los sistemas abstractos diseñados | D34: =IFERROR(__xludf.DUMMYFUNCTION("""COMPUTED_VALUE"""),"Perspectiva de sistemas abstractos diseñados") -> Perspectiva de sistemas abstractos diseñados | F34: =IFERROR(__xludf.DUMMYFUNCTION("""COMPUTED_VALUE"""),"Interrelaciones entre modelos mentales") -> Interrelaciones entre modelos mentales
B35: =IFERROR(__xludf.DUMMYFUNCTION("""COMPUTED_VALUE"""),"Unidad 2: Los sistemas abstractos diseñados") -> Unidad 2: Los sistemas abstractos diseñados | D35: =IFERROR(__xludf.DUMMYFUNCTION("""COMPUTED_VALUE"""),"Perspectiva de sistemas abstractos diseñados") -> Perspectiva de sistemas abstractos diseñados | F35: =IFERROR(__xludf.DUMMYFUNCTION("""COMPUTED_VALUE"""),"Ejemplos de pensamiento circular") -> Ejemplos de pensamiento circular
A36: 2.2 Recursos Educativos | B36: =IFERROR(__xludf.DUMMYFUNCTION("""COMPUTED_VALUE"""),"Unidad 2: Los sistemas abstractos diseñados") -> Unidad 2: Los sistemas abstractos diseñados | D36: =IFERROR(__xludf.DUMMYFUNCTION("""COMPUTED_VALUE"""),"Perspectiva de sistemas abstractos diseñados") -> Perspectiva de sistemas abstractos diseñados | F36: =IFERROR(__xludf.DUMMYFUNCTION("""COMPUTED_VALUE"""),"Ejemplos de retroalimentación") -> Ejemplos de retroalimentación
A38: Tipo de Recurso a utilizar | B38: Tipo | C38: Valor maximo recomendado en Minutos | D38: Tiempo Aproximado ( unicamente el valor de minutos ) | I38: Validacion
A39: Presentacion | B39: Obligatorio | C39: 30 | D39: 20 | I39: =IF(D39<=C39,"Correcto", "Corregir") -> Correcto
A40: Video | B40: Obligatorio | C40: 6 | D40: 5 | I40: =IF(D40<=C40,"Correcto", "Corregir") -> Correcto
A41: Lectura | B41: Optativo | C41: 10 | D41: 5 | I41: =IF(D41<=C41,"Correcto", "Corregir") -> Correcto
A42: Ejercicio Demostrativo | B42: Obligatorio | C42: 30 | D42: 10 | I42: =IF(D42<=C42,"Correcto", "Corregir") -> Correcto
A44: 3. Área de Habilidades (Saber Hacer) | G44: Tiempo Aproximado | H44: =B50 -> 45
G45: Tiene que estar en un rango de 30 a 50 minutos
A46: Actividad 1 (Obligatoria)
A47: Competencia que predomina en la actividad | B47: comprende los fundamentos conceptuales del pensamiento sistémico y la naturaleza de los sistemas de la realidad a través del estudio de teorías, modelos mentales y estructuras de retroalimentación para distinguir los sistemas naturales, físicos diseñados, abstractos diseñados y de actividad humana
A48: Tipo de Actividad | B48: Ejercicio practico
A49: Ponderación | B49: 1
A50: Tiempo Aproximado | B50: 45
A51: Coloca el tiempo que usar en la actividad, un tiempo sugerido 30 minutos
A52: Descripcion de la Actividad
A53: Se presentan 3-4 escenarios. El estudiante debe Comprender la dinámica e identificar dónde la causalidad es circular.
A57: Actividad 2 (Optativa puedes hacerla si lo consideras apropiado)
A58: Competencia que predomina en la actividad
A59: Tipo de Actividad
A60: Ponderación
A61: Tiempo Aproximado
A62: Coloca el tiempo que usar en la actividad, un tiempo sugerido 20 minutos
A63: Descripcion de la Actividad
A68: 3. Cierre | G68: Tiempo Aproximado | H68: =B70 -> 10
G69: Tiene que estar en un rango de 10 a 15 minutos
A70: Tiempo Aproximado | B70: 10
A71: Asignacion de Actividades
A72: "1. Conclusión (3 min): La esencia del pensamiento sistémico es la Retroalimentación. Dejar de pensar en líneas y empezar a pensar en círculos es crucial para el análisis. 2. Asignación de Actividades (7 min): Tarea Preparatoria Obligatoria (para Semana 5): Investigar las definiciones formales de Subsistema, Suprasistema, Sinergia y Emergencia. Buscar ejemplos de sistemas naturales y sistemas físicos diseñados (preparación para la clasificación)."
A74: Resuelve alguna duda, asigna las actividades que deben realizar, dudas de proyectos, etc

Sheet S.5
B2: Diseño de la Sesión de Laboratorio
B4: Curso | C4: ='Diseño'!C4 -> 722 - Teoría de Sistemas 1
B5: Semana | C5: 5
B6: Tiempo | C6: =H10+H21+H44+H68 -> 110
B7: Ponderación | C7: =B49+B60 -> 1
B8: Validación de Tiempo | C8: =IF(H44<=0, "❌ ERROR: La Actividad 1 debe tener un tiempo mayor a 0.", IF(H21>60, "❌ ERROR: El 'Área de Conocimiento' no puede exceder los 60 min.", IF((H10+H21+H44)<100, "❌ ERROR: El tiempo total debe ser de al menos 100 min.", "✅ VALIDACIÓN CORRECTA"))) -> ✅ VALIDACIÓN CORRECTA
A10: 1. Área Actitudinal (Saber Ser) | G10: Tiempo Aproximado | H10: =B13 -> 5
G11: Tiene que estar en un rango de 3 a 5 minutos
A12: Nombre del Valor | B12: Estructura y Curiosidad Científica
A13: Tiempo Aproximado | B13: 5
A14: Descripcion
A15: Interés por desentrañar la estructura formal (partes y relaciones) que define el comportamiento de los sistemas.
A17: Como se relaciona con los conocimientos de la sesion y se aplicaria
A18: Se relaciona con los Fundamentos del pensamiento sistémico. Permite al estudiante Analizar que el comportamiento de un sistema se explica por su estructura (subsistemas, límites) y propiedades emergentes, preparando el terreno para el modelado formal de ingeniería.
A21: 2. Área Conocimiento (Saber) | G21: Tiempo Aproximado | H21: =SUM(D39:H42) -> 50
G22: No puede exceder los 60 minutos
A23: Competencia a desarrollar | B23: Analiza .. los principios basicos de la teoría de sistemas y su importancia en la vida mediante modelos sistémicos y recursos gráficos para analizar el funcionamiento, la estructura y las interacciones de los sistemas en distintos entornos tecnológicos
A24: Competencia a desarrollar
A26: 2.1 Contenido
A27: No. | B27: Unidad | D27: Tema | F27: Sub Tema
A28: 1 | B28: =IFERROR(__xludf.DUMMYFUNCTION("FILTER('Diseño'!D:D,'Diseño'!H:H=$C$5)"),"Unidad 2: Los sistemas abstractos diseñados") -> Unidad 2: Los sistemas abstractos diseñados | D28: =IFERROR(__xludf.DUMMYFUNCTION("FILTER('Diseño'!E:E,'Diseño'!H:H=$C$5)"),"Perspectiva de sistemas abstractos diseñados") -> Perspectiva de sistemas abstractos diseñados | F28: =IFERROR(__xludf.DUMMYFUNCTION("FILTER('Diseño'!F:F,'Diseño'!H:H=$C$5)"),"Conclusión de los modelos mentales diseñados") -> Conclusión de los modelos mentales diseñados
A29: 2 | B29: =IFERROR(__xludf.DUMMYFUNCTION("""COMPUTED_VALUE"""),"Unidad 3: Desarrollando el pensamiento sistémico complejo") -> Unidad 3: Desarrollando el pensamiento sistémico complejo | D29: =IFERROR(__xludf.DUMMYFUNCTION("""COMPUTED_VALUE"""),"Fundamentos del pensamiento sistémico") -> Fundamentos del pensamiento sistémico | F29: =IFERROR(__xludf.DUMMYFUNCTION("""COMPUTED_VALUE"""),"Concepto de sistema") -> Concepto de sistema
A30: 3 | B30: =IFERROR(__xludf.DUMMYFUNCTION("""COMPUTED_VALUE"""),"Unidad 3: Desarrollando el pensamiento sistémico complejo") -> Unidad 3: Desarrollando el pensamiento sistémico complejo | D30: =IFERROR(__xludf.DUMMYFUNCTION("""COMPUTED_VALUE"""),"Fundamentos del pensamiento sistémico") -> Fundamentos del pensamiento sistémico | F30: =IFERROR(__xludf.DUMMYFUNCTION("""COMPUTED_VALUE"""),"Estructura de los sistemas") -> Estructura de los sistemas
A31: 4 | B31: =IFERROR(__xludf.DUMMYFUNCTION("""COMPUTED_VALUE"""),"Unidad 3: Desarrollando el pensamiento sistémico complejo") -> Unidad 3: Desarrollando el pensamiento sistémico complejo | D31: =IFERROR(__xludf.DUMMYFUNCTION("""COMPUTED_VALUE"""),"Fundamentos del pensamiento sistémico") -> Fundamentos del pensamiento sistémico | F31: =IFERROR(__xludf.DUMMYFUNCTION("""COMPUTED_VALUE"""),"Subsistemas y suprasistemas") -> Subsistemas y suprasistemas
A32: 5 | B32: =IFERROR(__xludf.DUMMYFUNCTION("""COMPUTED_VALUE"""),"Unidad 3: Desarrollando el pensamiento sistémico complejo") -> Unidad 3: Desarrollando el pensamiento sistémico complejo | D32: =IFERROR(__xludf.DUMMYFUNCTION("""COMPUTED_VALUE"""),"Fundamentos del pensamiento sistémico") -> Fundamentos del pensamiento sistémico | F32: =IFERROR(__xludf.DUMMYFUNCTION("""COMPUTED_VALUE"""),"Sinergia y emergencia en sistemas") -> Sinergia y emergencia en sistemas
A33: 6 | B33: =IFERROR(__xludf.DUMMYFUNCTION("""COMPUTED_VALUE"""),"Unidad 3: Desarrollando el pensamiento sistémico complejo") -> Unidad 3: Desarrollando el pensamiento sistémico complejo | D33: =IFERROR(__xludf.DUMMYFUNCTION("""COMPUTED_VALUE"""),"Fundamentos del pensamiento sistémico") -> Fundamentos del pensamiento sistémico | F33: =IFERROR(__xludf.DUMMYFUNCTION("""COMPUTED_VALUE"""),"Complejidad sistémica") -> Complejidad sistémica
A34: 7 | B34: =IFERROR(__xludf.DUMMYFUNCTION("""COMPUTED_VALUE"""),"Unidad 3: Desarrollando el pensamiento sistémico complejo") -> Unidad 3: Desarrollando el pensamiento sistémico complejo | D34: =IFERROR(__xludf.DUMMYFUNCTION("""COMPUTED_VALUE"""),"Fundamentos del pensamiento sistémico") -> Fundamentos del pensamiento sistémico | F34: =IFERROR(__xludf.DUMMYFUNCTION("""COMPUTED_VALUE"""),"El universo como conjunto de sistemas") -> El universo como conjunto de sistemas
B35: =IFERROR(__xludf.DUMMYFUNCTION("""COMPUTED_VALUE"""),"Unidad 3: Desarrollando el pensamiento sistémico complejo") -> Unidad 3: Desarrollando el pensamiento sistémico complejo | D35: =IFERROR(__xludf.DUMMYFUNCTION("""COMPUTED_VALUE"""),"Fundamentos del pensamiento sistémico") -> Fundamentos del pensamiento sistémico | F35: =IFERROR(__xludf.DUMMYFUNCTION("""COMPUTED_VALUE"""),"Ejemplos de sistemas naturales") -> Ejemplos de sistemas naturales
A36: 2.2 Recursos Educativos | B36: =IFERROR(__xludf.DUMMYFUNCTION("""COMPUTED_VALUE"""),"Unidad 3: Desarrollando el pensamiento sistémico complejo") -> Unidad 3: Desarrollando el pensamiento sistémico complejo | D36: =IFERROR(__xludf.DUMMYFUNCTION("""COMPUTED_VALUE"""),"Clasificación de sistemas") -> Clasificación de sistemas | F36: =IFERROR(__xludf.DUMMYFUNCTION("""COMPUTED_VALUE"""),"Sistemas físicos diseñados") -> Sistemas físicos diseñados
A38: Tipo de Recurso a utilizar | B38: Tipo | C38: Valor maximo recomendado en Minutos | D38: Tiempo Aproximado ( unicamente el valor de minutos ) | I38: Validacion
A39: Presentacion | B39: Obligatorio | C39: 30 | D39: 25 | I39: =IF(D39<=C39,"Correcto", "Corregir") -> Correcto
A40: Video | B40: Obligatorio | C40: 6 | D40: 5 | I40: =IF(D40<=C40,"Correcto", "Corregir") -> Correcto
A41: Lectura | B41: Optativo | C41: 10 | D41: 5 | I41: =IF(D41<=C41,"Correcto", "Corregir") -> Correcto
A42: Ejercicio Demostrativo | B42: Obligatorio | C42: 30 | D42: 15 | I42: =IF(D42<=C42,"Correcto", "Corregir") -> Correcto
A44: 3. Área de Habilidades (Saber Hacer) | G44: Tiempo Aproximado | H44: =B50 -> 45
G45: Tiene que estar en un rango de 30 a 50 minutos
A46: Actividad 1 (Obligatoria)
A47: Competencia que predomina en la actividad | B47: Analiza .. los principios basicos de la teoría de sistemas y su importancia en la vida mediante modelos sistémicos y recursos gráficos para analizar el funcionamiento, la estructura y las interacciones de los sistemas en distintos entornos tecnológicos
A48: Tipo de Actividad | B48: Analisis
A49: Ponderación | B49: 1
A50: Tiempo Aproximado | B50: 45
A51: Coloca el tiempo que usar en la actividad, un tiempo sugerido 30 minutos
A52: Descripcion de la Actividad
A53: se presentan varios sistemas (ej. un termostato, un ecosistema, un grupo de trabajo). Los estudiantes deben Analizar y clasificar cada uno: 1. Su origen. 2. Identificar los límites y los subsistemas. 3. Determinar si exhiben sinergia o emergencia y explicar por qué.
A57: Actividad 2 (Optativa puedes hacerla si lo consideras apropiado)
A58: Competencia que predomina en la actividad
A59: Tipo de Actividad
A60: Ponderación | B60: 0
A61: Tiempo Aproximado | B61: 10
A62: Coloca el tiempo que usar en la actividad, un tiempo sugerido 20 minutos
A63: Descripcion de la Actividad
A64: Se muestran tres conjuntos de polos de un sistema de 2do orden. Los estudiantes deben Analizar el conjunto de polos que produce: a) La respuesta más rápida; b) El mayor sobreimpulso.
A68: 3. Cierre | G68: Tiempo Aproximado | H68: =B70 -> 10
G69: Tiene que estar en un rango de 10 a 15 minutos
A70: Tiempo Aproximado | B70: 10
A71: Asignacion de Actividades
A72: Elegir un problema sistémico de baja a media complejidad (ej. un problema de gestión de inventario, un conflicto social, un problema de tráfico recurrente). Listar al menos 6 variables clave que están interconectadas y que podrían formar la base de un Diagrama de Ciclos Causales (DCC).
A74: Resuelve alguna duda, asigna las actividades que deben realizar, dudas de proyectos, etc

Sheet S.6
B2: Diseño de la Sesión de Laboratorio
B4: Curso | C4: ='Diseño'!C4 -> 722 - Teoría de Sistemas 1
B5: Semana | C5: 6
B6: Tiempo | C6: =H10+H21+H44+H68 -> 100
B7: Ponderación | C7: =B49+B60 -> 1
B8: Validación de Tiempo | C8: =IF(H44<=0, "❌ ERROR: La Actividad 1 debe tener un tiempo mayor a 0.", IF(H21>60, "❌ ERROR: El 'Área de Conocimiento' no puede exceder los 60 min.", IF((H10+H21+H44)<100, "❌ ERROR: El tiempo total debe ser de al menos 100 min.", "✅ VALIDACIÓN CORRECTA"))) -> ❌ ERROR: El tiempo total debe ser de al menos 100 min.
A10: 1. Área Actitudinal (Saber Ser) | G10: Tiempo Aproximado | H10: =B13 -> 5
G11: Tiene que estar en un rango de 3 a 5 minutos
A12: Nombre del Valor | B12: Vision Profunda
A13: Tiempo Aproximado | B13: 5
A14: Descripcion
A15: Tendencia a buscar las causas estructurales y los patrones, y no conformarse con la explicación superficial de los eventos.
A17: Como se relaciona con los conocimientos de la sesion y se aplicaria
A18: Se relaciona directamente con el Modelo del Iceberg. Fomenta que el estudiante Identifique los patrones y estructuras (debajo de la superficie) para ir más allá de los eventos (la punta del iceberg), un paso crucial en el análisis sistémico.
A21: 2. Área Conocimiento (Saber) | G21: Tiempo Aproximado | H21: =SUM(D39:H42) -> 55
G22: No puede exceder los 60 minutos
A23: Competencia a desarrollar | B23: Analiza .. los principios basicos de la teoría de sistemas y su importancia en la vida mediante modelos sistémicos y recursos gráficos para analizar el funcionamiento, la estructura y las interacciones de los sistemas en distintos entornos tecnológicos
A24: Competencia a desarrollar | B24: identifica los conceptos fundamentales de la teoría de sistemas y del pensamiento sistémico mediante la revisión de definiciones para reconocer los elementos esenciales en el análisis y modelación de sistemas
A26: 2.1 Contenido
A27: No. | B27: Unidad | D27: Tema | F27: Sub Tema
A28: 1 | B28: =IFERROR(__xludf.DUMMYFUNCTION("FILTER('Diseño'!D:D,'Diseño'!H:H=$C$5)"),"Unidad 3: Desarrollando el pensamiento sistémico complejo") -> Unidad 3: Desarrollando el pensamiento sistémico complejo | D28: =IFERROR(__xludf.DUMMYFUNCTION("FILTER('Diseño'!E:E,'Diseño'!H:H=$C$5)"),"Clasificación de sistemas") -> Clasificación de sistemas | F28: =IFERROR(__xludf.DUMMYFUNCTION("FILTER('Diseño'!F:F,'Diseño'!H:H=$C$5)"),"Sistemas abstractos diseñados") -> Sistemas abstractos diseñados
A29: 2 | B29: =IFERROR(__xludf.DUMMYFUNCTION("""COMPUTED_VALUE"""),"Unidad 3: Desarrollando el pensamiento sistémico complejo") -> Unidad 3: Desarrollando el pensamiento sistémico complejo | D29: =IFERROR(__xludf.DUMMYFUNCTION("""COMPUTED_VALUE"""),"Clasificación de sistemas") -> Clasificación de sistemas | F29: =IFERROR(__xludf.DUMMYFUNCTION("""COMPUTED_VALUE"""),"Sistemas de actividad humana") -> Sistemas de actividad humana
A30: 3 | B30: =IFERROR(__xludf.DUMMYFUNCTION("""COMPUTED_VALUE"""),"Unidad 3: Desarrollando el pensamiento sistémico complejo") -> Unidad 3: Desarrollando el pensamiento sistémico complejo | D30: =IFERROR(__xludf.DUMMYFUNCTION("""COMPUTED_VALUE"""),"Clasificación de sistemas") -> Clasificación de sistemas | F30: =IFERROR(__xludf.DUMMYFUNCTION("""COMPUTED_VALUE"""),"Diferencias entre sistemas naturales y diseñados") -> Diferencias entre sistemas naturales y diseñados
A31: 4 | B31: =IFERROR(__xludf.DUMMYFUNCTION("""COMPUTED_VALUE"""),"Unidad 3: Desarrollando el pensamiento sistémico complejo") -> Unidad 3: Desarrollando el pensamiento sistémico complejo | D31: =IFERROR(__xludf.DUMMYFUNCTION("""COMPUTED_VALUE"""),"Clasificación de sistemas") -> Clasificación de sistemas | F31: =IFERROR(__xludf.DUMMYFUNCTION("""COMPUTED_VALUE"""),"Sistemas complejos adaptativos") -> Sistemas complejos adaptativos
A32: 5 | B32: =IFERROR(__xludf.DUMMYFUNCTION("""COMPUTED_VALUE"""),"Unidad 3: Desarrollando el pensamiento sistémico complejo") -> Unidad 3: Desarrollando el pensamiento sistémico complejo | D32: =IFERROR(__xludf.DUMMYFUNCTION("""COMPUTED_VALUE"""),"Clasificación de sistemas") -> Clasificación de sistemas | F32: =IFERROR(__xludf.DUMMYFUNCTION("""COMPUTED_VALUE"""),"Características de sistemas de actividad humana") -> Características de sistemas de actividad humana
A33: 6 | B33: =IFERROR(__xludf.DUMMYFUNCTION("""COMPUTED_VALUE"""),"Unidad 3: Desarrollando el pensamiento sistémico complejo") -> Unidad 3: Desarrollando el pensamiento sistémico complejo | D33: =IFERROR(__xludf.DUMMYFUNCTION("""COMPUTED_VALUE"""),"Clasificación de sistemas") -> Clasificación de sistemas | F33: =IFERROR(__xludf.DUMMYFUNCTION("""COMPUTED_VALUE"""),"Ejemplos de interacciones entre sistemas") -> Ejemplos de interacciones entre sistemas
A34: 7 | B34: =IFERROR(__xludf.DUMMYFUNCTION("""COMPUTED_VALUE"""),"Unidad 3: Desarrollando el pensamiento sistémico complejo") -> Unidad 3: Desarrollando el pensamiento sistémico complejo | D34: =IFERROR(__xludf.DUMMYFUNCTION("""COMPUTED_VALUE"""),"Niveles de perspectiva") -> Niveles de perspectiva | F34: =IFERROR(__xludf.DUMMYFUNCTION("""COMPUTED_VALUE"""),"Modelo del iceberg") -> Modelo del iceberg
B35: =IFERROR(__xludf.DUMMYFUNCTION("""COMPUTED_VALUE"""),"Unidad 3: Desarrollando el pensamiento sistémico complejo") -> Unidad 3: Desarrollando el pensamiento sistémico complejo | D35: =IFERROR(__xludf.DUMMYFUNCTION("""COMPUTED_VALUE"""),"Niveles de perspectiva") -> Niveles de perspectiva | F35: =IFERROR(__xludf.DUMMYFUNCTION("""COMPUTED_VALUE"""),"Interpretación de niveles de percepción") -> Interpretación de niveles de percepción
A36: 2.2 Recursos Educativos | B36: =IFERROR(__xludf.DUMMYFUNCTION("""COMPUTED_VALUE"""),"Unidad 3: Desarrollando el pensamiento sistémico complejo") -> Unidad 3: Desarrollando el pensamiento sistémico complejo | D36: =IFERROR(__xludf.DUMMYFUNCTION("""COMPUTED_VALUE"""),"Niveles de perspectiva") -> Niveles de perspectiva | F36: =IFERROR(__xludf.DUMMYFUNCTION("""COMPUTED_VALUE"""),"Impacto de la percepción en el pensamiento sistémico") -> Impacto de la percepción en el pensamiento sistémico
B37: =IFERROR(__xludf.DUMMYFUNCTION("""COMPUTED_VALUE"""),"Unidad 3: Desarrollando el pensamiento sistémico complejo") -> Unidad 3: Desarrollando el pensamiento sistémico complejo | D37: =IFERROR(__xludf.DUMMYFUNCTION("""COMPUTED_VALUE"""),"Niveles de perspectiva") -> Niveles de perspectiva | F37: =IFERROR(__xludf.DUMMYFUNCTION("""COMPUTED_VALUE"""),"Ejemplos de interpretación de sistemas") -> Ejemplos de interpretación de sistemas
A38: Tipo de Recurso a utilizar | B38: Tipo | C38: Valor maximo recomendado en Minutos | D38: Tiempo Aproximado ( unicamente el valor de minutos ) | I38: Validacion
A39: Presentacion | B39: Obligatorio | C39: 30 | D39: 15 | I39: =IF(D39<=C39,"Correcto", "Corregir") -> Correcto
A40: Video | B40: Obligatorio | C40: 6 | D40: 5 | I40: =IF(D40<=C40,"Correcto", "Corregir") -> Correcto
A41: Lectura | B41: Optativo | C41: 10 | D41: 5 | I41: =IF(D41<=C41,"Correcto", "Corregir") -> Correcto
A42: Ejercicio Demostrativo | B42: Obligatorio | C42: 30 | D42: 30 | I42: =IF(D42<=C42,"Correcto", "Corregir") -> Correcto
A44: 3. Área de Habilidades (Saber Hacer) | G44: Tiempo Aproximado | H44: =B50 -> 30
G45: Tiene que estar en un rango de 30 a 50 minutos
A46: Actividad 1 (Obligatoria)
A47: Competencia que predomina en la actividad | B47: Analiza .. los principios basicos de la teoría de sistemas y su importancia en la vida mediante modelos sistémicos y recursos gráficos para analizar el funcionamiento, la estructura y las interacciones de los sistemas en distintos entornos tecnológicos
A48: Tipo de Actividad | B48: Analisis
A49: Ponderación | B49: 1
A50: Tiempo Aproximado | B50: 30
A51: Coloca el tiempo que usar en la actividad, un tiempo sugerido 30 minutos
A52: Descripcion de la Actividad
A53: Los estudiantes reciben un problema basado en eventos (ej. "Las ventas bajaron este mes"). Deben Analizar el problema usando el Modelo del Iceberg: 1. Eventos: Describir lo que pasó. 2. Patrones: Identificar tendencias históricas. 3. Estructuras: Hipotetizar qué mecanismos causan los patrones (ej. estructura de comisiones). 4. Modelos Mentales: Identificar el paradigma que sostiene la estructura (ej. "Solo hay que culpar a los vendedores").
A57: Actividad 2 (Optativa puedes hacerla si lo consideras apropiado)
A58: Competencia que predomina en la actividad
A59: Tipo de Actividad
A60: Ponderación
A61: Tiempo Aproximado
A62: Coloca el tiempo que usar en la actividad, un tiempo sugerido 20 minutos
A63: Descripcion de la Actividad
A68: 3. Cierre | G68: Tiempo Aproximado | H68: =B70 -> 10
G69: Tiene que estar en un rango de 10 a 15 minutos
A70: Tiempo Aproximado | B70: 10
A71: Asignacion de Actividades
A72: 1. Conclusión (3 min): El Modelo del Iceberg es la herramienta clave para pasar del pensamiento reactivo (eventos) al pensamiento creativo (estructuras). El verdadero cambio ocurre al modificar los modelos mentales. 2. Asignación de Actividades (7 min): Tarea Preparatoria Obligatoria (para Semana 7): Elegir un problema de la vida diaria y aplicar el Modelo del Iceberg, identificando un evento clave y al menos una Estructura subyacente que lo alimenta. Luego, investigar 3-5 Hábitos clave de un pensador sistémico.
A74: Resuelve alguna duda, asigna las actividades que deben realizar, dudas de proyectos, etc

Sheet S.7
B2: Diseño de la Sesión de Laboratorio
B4: Curso | C4: ='Diseño'!C4 -> 722 - Teoría de Sistemas 1
B5: Semana | C5: 7
B6: Tiempo | C6: =H10+H21+H44+H68 -> 100
B7: Ponderación | C7: =B49+B60 -> 1
B8: Validación de Tiempo | C8: =IF(H44<=0, "❌ ERROR: La Actividad 1 debe tener un tiempo mayor a 0.", IF(H21>60, "❌ ERROR: El 'Área de Conocimiento' no puede exceder los 60 min.", IF((H10+H21+H44)<100, "❌ ERROR: El tiempo total debe ser de al menos 100 min.", "✅ VALIDACIÓN CORRECTA"))) -> ❌ ERROR: El tiempo total debe ser de al menos 100 min.
A10: 1. Área Actitudinal (Saber Ser) | G10: Tiempo Aproximado | H10: =B13 -> 5
G11: Tiene que estar en un rango de 3 a 5 minutos
A12: Nombre del Valor | B12: Intención y Práctica
A13: Tiempo Aproximado | B13: 5
A14: Descripcion
A15: La disciplina consciente para adoptar las prácticas sistémicas en la vida diaria.
A17: Como se relaciona con los conocimientos de la sesion y se aplicaria
A18: Se relaciona con los Hábitos de un Pensador Sistémico. Fomenta que el estudiante Comprenda que el pensamiento sistémico no es solo conocimiento, sino un conjunto de prácticas intencionales (hábitos) que mejoran la toma de decisiones a largo plazo.
A21: 2. Área Conocimiento (Saber) | G21: Tiempo Aproximado | H21: =SUM(D39:H42) -> 50
G22: No puede exceder los 60 minutos
A23: Competencia a desarrollar | B23: comprende los fundamentos conceptuales del pensamiento sistémico y la naturaleza de los sistemas de la realidad a través del estudio de teorías, modelos mentales y estructuras de retroalimentación para distinguir los sistemas naturales, físicos diseñados, abstractos diseñados y de actividad humana
A24: Competencia a desarrollar
A26: 2.1 Contenido
A27: No. | B27: Unidad | D27: Tema | F27: Sub Tema
A28: 1 | B28: =IFERROR(__xludf.DUMMYFUNCTION("FILTER('Diseño'!D:D,'Diseño'!H:H=$C$5)"),"Unidad 3: Desarrollando el pensamiento sistémico complejo") -> Unidad 3: Desarrollando el pensamiento sistémico complejo | D28: =IFERROR(__xludf.DUMMYFUNCTION("FILTER('Diseño'!E:E,'Diseño'!H:H=$C$5)"),"Niveles de perspectiva") -> Niveles de perspectiva | F28: =IFERROR(__xludf.DUMMYFUNCTION("FILTER('Diseño'!F:F,'Diseño'!H:H=$C$5)"),"Cambio de perspectiva en análisis sistémico") -> Cambio de perspectiva en análisis sistémico
A29: 2 | B29: =IFERROR(__xludf.DUMMYFUNCTION("""COMPUTED_VALUE"""),"Unidad 3: Desarrollando el pensamiento sistémico complejo") -> Unidad 3: Desarrollando el pensamiento sistémico complejo | D29: =IFERROR(__xludf.DUMMYFUNCTION("""COMPUTED_VALUE"""),"Niveles de perspectiva") -> Niveles de perspectiva | F29: =IFERROR(__xludf.DUMMYFUNCTION("""COMPUTED_VALUE"""),"Impacto del cambio de nivel de percepción") -> Impacto del cambio de nivel de percepción
A30: 3 | B30: =IFERROR(__xludf.DUMMYFUNCTION("""COMPUTED_VALUE"""),"Unidad 3: Desarrollando el pensamiento sistémico complejo") -> Unidad 3: Desarrollando el pensamiento sistémico complejo | D30: =IFERROR(__xludf.DUMMYFUNCTION("""COMPUTED_VALUE"""),"Niveles de perspectiva") -> Niveles de perspectiva | F30: =IFERROR(__xludf.DUMMYFUNCTION("""COMPUTED_VALUE"""),"Ejemplos de interacción entre niveles de perspectiva") -> Ejemplos de interacción entre niveles de perspectiva
A31: 4 | B31: =IFERROR(__xludf.DUMMYFUNCTION("""COMPUTED_VALUE"""),"Unidad 3: Desarrollando el pensamiento sistémico complejo") -> Unidad 3: Desarrollando el pensamiento sistémico complejo | D31: =IFERROR(__xludf.DUMMYFUNCTION("""COMPUTED_VALUE"""),"Hábitos de un pensador sistémico") -> Hábitos de un pensador sistémico | F31: =IFERROR(__xludf.DUMMYFUNCTION("""COMPUTED_VALUE"""),"Introducción a los hábitos de un pensador sistémico") -> Introducción a los hábitos de un pensador sistémico
A32: 5 | B32: =IFERROR(__xludf.DUMMYFUNCTION("""COMPUTED_VALUE"""),"Unidad 3: Desarrollando el pensamiento sistémico complejo") -> Unidad 3: Desarrollando el pensamiento sistémico complejo | D32: =IFERROR(__xludf.DUMMYFUNCTION("""COMPUTED_VALUE"""),"Hábitos de un pensador sistémico") -> Hábitos de un pensador sistémico | F32: =IFERROR(__xludf.DUMMYFUNCTION("""COMPUTED_VALUE"""),"Ejemplos de hábitos de pensamiento sistémico") -> Ejemplos de hábitos de pensamiento sistémico
A33: 6 | B33: =IFERROR(__xludf.DUMMYFUNCTION("""COMPUTED_VALUE"""),"Unidad 3: Desarrollando el pensamiento sistémico complejo") -> Unidad 3: Desarrollando el pensamiento sistémico complejo | D33: =IFERROR(__xludf.DUMMYFUNCTION("""COMPUTED_VALUE"""),"Hábitos de un pensador sistémico") -> Hábitos de un pensador sistémico | F33: =IFERROR(__xludf.DUMMYFUNCTION("""COMPUTED_VALUE"""),"Aplicación de hábitos en la vida diaria") -> Aplicación de hábitos en la vida diaria
A34: 7 | B34: =IFERROR(__xludf.DUMMYFUNCTION("""COMPUTED_VALUE"""),"Unidad 3: Desarrollando el pensamiento sistémico complejo") -> Unidad 3: Desarrollando el pensamiento sistémico complejo | D34: =IFERROR(__xludf.DUMMYFUNCTION("""COMPUTED_VALUE"""),"Hábitos de un pensador sistémico") -> Hábitos de un pensador sistémico | F34: =IFERROR(__xludf.DUMMYFUNCTION("""COMPUTED_VALUE"""),"Relación entre hábitos y toma de decisiones") -> Relación entre hábitos y toma de decisiones
B35: =IFERROR(__xludf.DUMMYFUNCTION("""COMPUTED_VALUE"""),"Unidad 3: Desarrollando el pensamiento sistémico complejo") -> Unidad 3: Desarrollando el pensamiento sistémico complejo | D35: =IFERROR(__xludf.DUMMYFUNCTION("""COMPUTED_VALUE"""),"Hábitos de un pensador sistémico") -> Hábitos de un pensador sistémico | F35: =IFERROR(__xludf.DUMMYFUNCTION("""COMPUTED_VALUE"""),"Mejora de habilidades de pensamiento sistémico") -> Mejora de habilidades de pensamiento sistémico
A36: 2.2 Recursos Educativos | B36: =IFERROR(__xludf.DUMMYFUNCTION("""COMPUTED_VALUE"""),"Unidad 3: Desarrollando el pensamiento sistémico complejo") -> Unidad 3: Desarrollando el pensamiento sistémico complejo | D36: =IFERROR(__xludf.DUMMYFUNCTION("""COMPUTED_VALUE"""),"Hábitos de un pensador sistémico") -> Hábitos de un pensador sistémico | F36: =IFERROR(__xludf.DUMMYFUNCTION("""COMPUTED_VALUE"""),"Desarrollo de la perspectiva a largo plazo") -> Desarrollo de la perspectiva a largo plazo
A38: Tipo de Recurso a utilizar | B38: Tipo | C38: Valor maximo recomendado en Minutos | D38: Tiempo Aproximado ( unicamente el valor de minutos ) | I38: Validacion
A39: Presentacion | B39: Obligatorio | C39: 30 | D39: 15 | I39: =IF(D39<=C39,"Correcto", "Corregir") -> Correcto
A40: Video | B40: Obligatorio | C40: 6 | D40: 5 | I40: =IF(D40<=C40,"Correcto", "Corregir") -> Correcto
A41: Lectura | B41: Optativo | C41: 10 | D41: 5 | I41: =IF(D41<=C41,"Correcto", "Corregir") -> Correcto
A42: Ejercicio Demostrativo | B42: Obligatorio | C42: 30 | D42: 25 | I42: =IF(D42<=C42,"Correcto", "Corregir") -> Correcto
A44: 3. Área de Habilidades (Saber Hacer) | G44: Tiempo Aproximado | H44: =B50 -> 35
G45: Tiene que estar en un rango de 30 a 50 minutos
A46: Actividad 1 (Obligatoria)
A47: Competencia que predomina en la actividad | B47: comprende los fundamentos conceptuales del pensamiento sistémico y la naturaleza de los sistemas de la realidad a través del estudio de teorías, modelos mentales y estructuras de retroalimentación para distinguir los sistemas naturales, físicos diseñados, abstractos diseñados y de actividad humana
A48: Tipo de Actividad | B48: otros
A49: Ponderación | B49: 1
A50: Tiempo Aproximado | B50: 35
A51: Coloca el tiempo que usar en la actividad, un tiempo sugerido 30 minutos
A52: Descripcion de la Actividad
A53: Los estudiantes reciben un dilema de ingeniería/gestión (ej. "Elegir un proveedor más barato vs. uno más confiable"). Deben Comprender y debatir: 1. ¿Cómo se aplicaría el hábito de buscar el bucle (retroalimentación) en esta decisión? 2. ¿Cómo se aplicaría el hábito de ver a largo plazo? 3. Sugerir una decisión basada en dos hábitos sistémicos.
A57: Actividad 2 (Optativa puedes hacerla si lo consideras apropiado)
A58: Competencia que predomina en la actividad
A59: Tipo de Actividad
A60: Ponderación
A61: Tiempo Aproximado
A62: Coloca el tiempo que usar en la actividad, un tiempo sugerido 20 minutos
A63: Descripcion de la Actividad
A68: 3. Cierre | G68: Tiempo Aproximado | H68: =B70 -> 10
G69: Tiene que estar en un rango de 10 a 15 minutos
A70: Tiempo Aproximado | B70: 10
A71: Asignacion de Actividades
A72: 1. Conclusión (5 min): Los hábitos son las "operaciones mentales" automatizadas que transforman la forma en que interactuamos con el sistema. La perspectiva a largo plazo es esencial. 2. Asignación de Actividades (10 min): Tarea Preparatoria Obligatoria (para Semana 8): Investigar los componentes de los Mapas DSRP (Distinciones, Sistemas, Relaciones, Perspectivas) y un tutorial básico sobre la construcción de Diagramas de Causa y Efecto para formalizar las interdependencias.
A74: Resuelve alguna duda, asigna las actividades que deben realizar, dudas de proyectos, etc

Sheet S.8
B2: Diseño de la Sesión de Laboratorio
B4: Curso | C4: ='Diseño'!C4 -> 722 - Teoría de Sistemas 1
B5: Semana | C5: 8
B6: Tiempo | C6: =H10+H21+H44+H68 -> 100
B7: Ponderación | C7: =B49+B60 -> 1
B8: Validación de Tiempo | C8: =IF(H44<=0, "❌ ERROR: La Actividad 1 debe tener un tiempo mayor a 0.", IF(H21>60, "❌ ERROR: El 'Área de Conocimiento' no puede exceder los 60 min.", IF((H10+H21+H44)<100, "❌ ERROR: El tiempo total debe ser de al menos 100 min.", "✅ VALIDACIÓN CORRECTA"))) -> ❌ ERROR: El tiempo total debe ser de al menos 100 min.
A10: 1. Área Actitudinal (Saber Ser) | G10: Tiempo Aproximado | H10: =B13 -> 5
G11: Tiene que estar en un rango de 3 a 5 minutos
A12: Nombre del Valor | B12: Articulación Lógica
A13: Tiempo Aproximado | B13: 5
A14: Descripcion
A15: Habilidad de traducir una idea compleja a un modelo visual y estructurado.
A17: Como se relaciona con los conocimientos de la sesion y se aplicaria
A18: Se relaciona con los Mapas DSRP y Diagramas de Causa y Efecto. Fomenta que el estudiante Analice y estructure las interdependencias sistémicas de manera formal y lógica, un paso esencial para la modelación.
A21: 2. Área Conocimiento (Saber) | G21: Tiempo Aproximado | H21: =SUM(D39:H42) -> 55
G22: No puede exceder los 60 minutos
A23: Competencia a desarrollar | B23: Analiza .. los principios basicos de la teoría de sistemas y su importancia en la vida mediante modelos sistémicos y recursos gráficos para analizar el funcionamiento, la estructura y las interacciones de los sistemas en distintos entornos tecnológicos
A24: Competencia a desarrollar
A26: 2.1 Contenido
A27: No. | B27: Unidad | D27: Tema | F27: Sub Tema
A28: 1 | B28: =IFERROR(__xludf.DUMMYFUNCTION("FILTER('Diseño'!D:D,'Diseño'!H:H=$C$5)"),"Unidad 3: Desarrollando el pensamiento sistémico complejo") -> Unidad 3: Desarrollando el pensamiento sistémico complejo | D28: =IFERROR(__xludf.DUMMYFUNCTION("FILTER('Diseño'!E:E,'Diseño'!H:H=$C$5)"),"Hábitos de un pensador sistémico") -> Hábitos de un pensador sistémico | F28: =IFERROR(__xludf.DUMMYFUNCTION("FILTER('Diseño'!F:F,'Diseño'!H:H=$C$5)"),"Casos de estudio") -> Casos de estudio
A29: 2 | B29: =IFERROR(__xludf.DUMMYFUNCTION("""COMPUTED_VALUE"""),"Unidad 4: Modelación y simulación dinámica de sistemas") -> Unidad 4: Modelación y simulación dinámica de sistemas | D29: =IFERROR(__xludf.DUMMYFUNCTION("""COMPUTED_VALUE"""),"Modelación de sistemas con mapas sistémicos") -> Modelación de sistemas con mapas sistémicos | F29: =IFERROR(__xludf.DUMMYFUNCTION("""COMPUTED_VALUE"""),"Introducción a los mapas sistémicos") -> Introducción a los mapas sistémicos
A30: 3 | B30: =IFERROR(__xludf.DUMMYFUNCTION("""COMPUTED_VALUE"""),"Unidad 4: Modelación y simulación dinámica de sistemas") -> Unidad 4: Modelación y simulación dinámica de sistemas | D30: =IFERROR(__xludf.DUMMYFUNCTION("""COMPUTED_VALUE"""),"Modelación de sistemas con mapas sistémicos") -> Modelación de sistemas con mapas sistémicos | F30: =IFERROR(__xludf.DUMMYFUNCTION("""COMPUTED_VALUE"""),"Mapas DSRP") -> Mapas DSRP
A31: 4 | B31: =IFERROR(__xludf.DUMMYFUNCTION("""COMPUTED_VALUE"""),"Unidad 4: Modelación y simulación dinámica de sistemas") -> Unidad 4: Modelación y simulación dinámica de sistemas | D31: =IFERROR(__xludf.DUMMYFUNCTION("""COMPUTED_VALUE"""),"Modelación de sistemas con mapas sistémicos") -> Modelación de sistemas con mapas sistémicos | F31: =IFERROR(__xludf.DUMMYFUNCTION("""COMPUTED_VALUE"""),"Diagramas de causa y efecto") -> Diagramas de causa y efecto
A32: 5 | B32: =IFERROR(__xludf.DUMMYFUNCTION("""COMPUTED_VALUE"""),"Unidad 4: Modelación y simulación dinámica de sistemas") -> Unidad 4: Modelación y simulación dinámica de sistemas | D32: =IFERROR(__xludf.DUMMYFUNCTION("""COMPUTED_VALUE"""),"Modelación de sistemas con mapas sistémicos") -> Modelación de sistemas con mapas sistémicos | F32: =IFERROR(__xludf.DUMMYFUNCTION("""COMPUTED_VALUE"""),"Interdependencias sistémicas") -> Interdependencias sistémicas
A33: 6 | B33: =IFERROR(__xludf.DUMMYFUNCTION("""COMPUTED_VALUE"""),"Unidad 4: Modelación y simulación dinámica de sistemas") -> Unidad 4: Modelación y simulación dinámica de sistemas | D33: =IFERROR(__xludf.DUMMYFUNCTION("""COMPUTED_VALUE"""),"Modelación de sistemas con mapas sistémicos") -> Modelación de sistemas con mapas sistémicos | F33: =IFERROR(__xludf.DUMMYFUNCTION("""COMPUTED_VALUE"""),"Comportamientos circulares en sistemas") -> Comportamientos circulares en sistemas
A34: 7 | B34: =IFERROR(__xludf.DUMMYFUNCTION("""COMPUTED_VALUE"""),"Unidad 4: Modelación y simulación dinámica de sistemas") -> Unidad 4: Modelación y simulación dinámica de sistemas | D34: =IFERROR(__xludf.DUMMYFUNCTION("""COMPUTED_VALUE"""),"Modelación de sistemas con mapas sistémicos") -> Modelación de sistemas con mapas sistémicos | F34: =IFERROR(__xludf.DUMMYFUNCTION("""COMPUTED_VALUE"""),"Ejemplos de interdependencias sistémicas") -> Ejemplos de interdependencias sistémicas
B35: =IFERROR(__xludf.DUMMYFUNCTION("""COMPUTED_VALUE"""),"Unidad 4: Modelación y simulación dinámica de sistemas") -> Unidad 4: Modelación y simulación dinámica de sistemas | D35: =IFERROR(__xludf.DUMMYFUNCTION("""COMPUTED_VALUE"""),"Modelación de sistemas con mapas sistémicos") -> Modelación de sistemas con mapas sistémicos | F35: =IFERROR(__xludf.DUMMYFUNCTION("""COMPUTED_VALUE"""),"Introducción a la retroalimentación") -> Introducción a la retroalimentación
A36: 2.2 Recursos Educativos | B36: =IFERROR(__xludf.DUMMYFUNCTION("""COMPUTED_VALUE"""),"Unidad 4: Modelación y simulación dinámica de sistemas") -> Unidad 4: Modelación y simulación dinámica de sistemas | D36: =IFERROR(__xludf.DUMMYFUNCTION("""COMPUTED_VALUE"""),"Estructuras circulares de retroalimentación") -> Estructuras circulares de retroalimentación | F36: =IFERROR(__xludf.DUMMYFUNCTION("""COMPUTED_VALUE"""),"Retroalimentación de compensación y refuerzo") -> Retroalimentación de compensación y refuerzo
A38: Tipo de Recurso a utilizar | B38: Tipo | C38: Valor maximo recomendado en Minutos | D38: Tiempo Aproximado ( unicamente el valor de minutos ) | I38: Validacion
A39: Presentacion | B39: Obligatorio | C39: 30 | D39: 15 | I39: =IF(D39<=C39,"Correcto", "Corregir") -> Correcto
A40: Video | B40: Obligatorio | C40: 6 | D40: 5 | I40: =IF(D40<=C40,"Correcto", "Corregir") -> Correcto
A41: Lectura | B41: Optativo | C41: 10 | D41: 5 | I41: =IF(D41<=C41,"Correcto", "Corregir") -> Correcto
A42: Ejercicio Demostrativo | B42: Obligatorio | C42: 30 | D42: 30 | I42: =IF(D42<=C42,"Correcto", "Corregir") -> Correcto
A44: 3. Área de Habilidades (Saber Hacer) | G44: Tiempo Aproximado | H44: =B50 -> 30
G45: Tiene que estar en un rango de 30 a 50 minutos
A46: Actividad 1 (Obligatoria)
A47: Competencia que predomina en la actividad | B47: Analiza .. los principios basicos de la teoría de sistemas y su importancia en la vida mediante modelos sistémicos y recursos gráficos para analizar el funcionamiento, la estructura y las interacciones de los sistemas en distintos entornos tecnológicos
A48: Tipo de Actividad | B48: Ejercicio practico
A49: Ponderación | B49: 1
A50: Tiempo Aproximado | B50: 30
A51: Coloca el tiempo que usar en la actividad, un tiempo sugerido 30 minutos
A52: Descripcion de la Actividad
A53: Los estudiantes reciben un sistema conceptual (ej. la dinámica de un grupo de estudio o el uso de un recurso natural). Deben Analizar el sistema para: 1. Modelar las variables y las relaciones con flechas. 2. Identificar y distinguir las interdependencias sistémicas y bucles circulares. 3. Señalar si alguna relación es de Refuerzo (R) o Compensación (C) de manera informal.
A57: Actividad 2 (Optativa puedes hacerla si lo consideras apropiado)
A58: Competencia que predomina en la actividad
A59: Tipo de Actividad
A60: Ponderación
A61: Tiempo Aproximado
A62: Coloca el tiempo que usar en la actividad, un tiempo sugerido 20 minutos
A63: Descripcion de la Actividad
A68: 3. Cierre | G68: Tiempo Aproximado | H68: =B70 -> 10
G69: Tiene que estar en un rango de 10 a 15 minutos
A70: Tiempo Aproximado | B70: 10
A71: Asignacion de Actividades
A72: 1. Conclusión (5 min): Los mapas sistémicos y el DSRP son el "lenguaje" visual para articular las interdependencias. La identificación de la retroalimentación (R y C) es el paso más importante para entender la dinámica. 2. Asignación de Actividades (10 min): Tarea Preparatoria Obligatoria (para Semana 9): Formalizar el entendimiento de la retroalimentación. Investigar la notación y el procedimiento para construir un Diagrama de Ciclos Causales (DCC) (variables, flechas, polaridades +/−, identificación de bucles R/C).
A74: Resuelve alguna duda, asigna las actividades que deben realizar, dudas de proyectos, etc

Sheet S.9
B2: Diseño de la Sesión de Laboratorio
B4: Curso | C4: ='Diseño'!C4 -> 722 - Teoría de Sistemas 1
B5: Semana | C5: 9
B6: Tiempo | C6: =H10+H21+H44+H68 -> 100
B7: Ponderación | C7: =B49+B60 -> 1
B8: Validación de Tiempo | C8: =IF(H44<=0, "❌ ERROR: La Actividad 1 debe tener un tiempo mayor a 0.", IF(H21>60, "❌ ERROR: El 'Área de Conocimiento' no puede exceder los 60 min.", IF((H10+H21+H44)<100, "❌ ERROR: El tiempo total debe ser de al menos 100 min.", "✅ VALIDACIÓN CORRECTA"))) -> ❌ ERROR: El tiempo total debe ser de al menos 100 min.
A10: 1. Área Actitudinal (Saber Ser) | G10: Tiempo Aproximado | H10: =B13 -> 5
G11: Tiene que estar en un rango de 3 a 5 minutos
A12: Nombre del Valor | B12: Dinamización
A13: Tiempo Aproximado | B13: 5
A14: Descripcion
A15: La disciplina de ver los sistemas no como fotos estáticas, sino como procesos que cambian con el tiempo.
A17: Como se relaciona con los conocimientos de la sesion y se aplicaria
A18: Se relaciona con los Ciclos Causales y las Acumulaciones. Fomenta que el estudiante Analice cómo la retroalimentación y las tasas de cambio (flujos) generan el patrón de comportamiento a lo largo del tiempo, no solo la causa y efecto inmediato.
A21: 2. Área Conocimiento (Saber) | G21: Tiempo Aproximado | H21: =SUM(D39:H42) -> 55
G22: No puede exceder los 60 minutos
A23: Competencia a desarrollar | B23: Analiza .. los principios basicos de la teoría de sistemas y su importancia en la vida mediante modelos sistémicos y recursos gráficos para analizar el funcionamiento, la estructura y las interacciones de los sistemas en distintos entornos tecnológicos
A24: Competencia a desarrollar
A26: 2.1 Contenido
A27: No. | B27: Unidad | D27: Tema | F27: Sub Tema
A28: 1 | B28: =IFERROR(__xludf.DUMMYFUNCTION("FILTER('Diseño'!D:D,'Diseño'!H:H=$C$5)"),"Unidad 4: Modelación y simulación dinámica de sistemas") -> Unidad 4: Modelación y simulación dinámica de sistemas | D28: =IFERROR(__xludf.DUMMYFUNCTION("FILTER('Diseño'!E:E,'Diseño'!H:H=$C$5)"),"Estructuras circulares de retroalimentación") -> Estructuras circulares de retroalimentación | F28: =IFERROR(__xludf.DUMMYFUNCTION("FILTER('Diseño'!F:F,'Diseño'!H:H=$C$5)"),"Ejemplos de retroalimentación en sistemas") -> Ejemplos de retroalimentación en sistemas
A29: 2 | B29: =IFERROR(__xludf.DUMMYFUNCTION("""COMPUTED_VALUE"""),"Unidad 4: Modelación y simulación dinámica de sistemas") -> Unidad 4: Modelación y simulación dinámica de sistemas | D29: =IFERROR(__xludf.DUMMYFUNCTION("""COMPUTED_VALUE"""),"Estructuras circulares de retroalimentación") -> Estructuras circulares de retroalimentación | F29: =IFERROR(__xludf.DUMMYFUNCTION("""COMPUTED_VALUE"""),"Impacto de la retroalimentación en el comportamiento de sistemas") -> Impacto de la retroalimentación en el comportamiento de sistemas
A30: 3 | B30: =IFERROR(__xludf.DUMMYFUNCTION("""COMPUTED_VALUE"""),"Unidad 4: Modelación y simulación dinámica de sistemas") -> Unidad 4: Modelación y simulación dinámica de sistemas | D30: =IFERROR(__xludf.DUMMYFUNCTION("""COMPUTED_VALUE"""),"Estructuras circulares de retroalimentación") -> Estructuras circulares de retroalimentación | F30: =IFERROR(__xludf.DUMMYFUNCTION("""COMPUTED_VALUE"""),"Retroalimentación y toma de decisiones") -> Retroalimentación y toma de decisiones
A31: 4 | B31: =IFERROR(__xludf.DUMMYFUNCTION("""COMPUTED_VALUE"""),"Unidad 4: Modelación y simulación dinámica de sistemas") -> Unidad 4: Modelación y simulación dinámica de sistemas | D31: =IFERROR(__xludf.DUMMYFUNCTION("""COMPUTED_VALUE"""),"Estructuras circulares de retroalimentación") -> Estructuras circulares de retroalimentación | F31: =IFERROR(__xludf.DUMMYFUNCTION("""COMPUTED_VALUE"""),"Acumulaciones y tasas de cambio ") -> Acumulaciones y tasas de cambio
A32: 5 | B32: =IFERROR(__xludf.DUMMYFUNCTION("""COMPUTED_VALUE"""),"Unidad 4: Modelación y simulación dinámica de sistemas") -> Unidad 4: Modelación y simulación dinámica de sistemas | D32: =IFERROR(__xludf.DUMMYFUNCTION("""COMPUTED_VALUE"""),"Estructuras circulares de retroalimentación") -> Estructuras circulares de retroalimentación | F32: =IFERROR(__xludf.DUMMYFUNCTION("""COMPUTED_VALUE"""),"Diagramas de ciclos causales a flujos y niveles") -> Diagramas de ciclos causales a flujos y niveles
A33: 6 | B33: =IFERROR(__xludf.DUMMYFUNCTION("""COMPUTED_VALUE"""),"Unidad 4: Modelación y simulación dinámica de sistemas") -> Unidad 4: Modelación y simulación dinámica de sistemas | D33: =IFERROR(__xludf.DUMMYFUNCTION("""COMPUTED_VALUE"""),"Estructuras circulares de retroalimentación") -> Estructuras circulares de retroalimentación | F33: =IFERROR(__xludf.DUMMYFUNCTION("""COMPUTED_VALUE"""),"Ejemplos de ciclos causales") -> Ejemplos de ciclos causales
A34: 7 | B34: =IFERROR(__xludf.DUMMYFUNCTION("""COMPUTED_VALUE"""),"Unidad 4: Modelación y simulación dinámica de sistemas") -> Unidad 4: Modelación y simulación dinámica de sistemas | D34: =IFERROR(__xludf.DUMMYFUNCTION("""COMPUTED_VALUE"""),"Simulación con VENSIM") -> Simulación con VENSIM | F34: =IFERROR(__xludf.DUMMYFUNCTION("""COMPUTED_VALUE"""),"Introducción a VENSIM") -> Introducción a VENSIM
B35: =IFERROR(__xludf.DUMMYFUNCTION("""COMPUTED_VALUE"""),"Unidad 4: Modelación y simulación dinámica de sistemas") -> Unidad 4: Modelación y simulación dinámica de sistemas | D35: =IFERROR(__xludf.DUMMYFUNCTION("""COMPUTED_VALUE"""),"Simulación con VENSIM") -> Simulación con VENSIM | F35: =IFERROR(__xludf.DUMMYFUNCTION("""COMPUTED_VALUE"""),"Ejemplos de simulaciones en VENSIM") -> Ejemplos de simulaciones en VENSIM
A36: 2.2 Recursos Educativos | B36: =IFERROR(__xludf.DUMMYFUNCTION("""COMPUTED_VALUE"""),"Unidad 4: Modelación y simulación dinámica de sistemas") -> Unidad 4: Modelación y simulación dinámica de sistemas | D36: =IFERROR(__xludf.DUMMYFUNCTION("""COMPUTED_VALUE"""),"Simulación con VENSIM") -> Simulación con VENSIM | F36: =IFERROR(__xludf.DUMMYFUNCTION("""COMPUTED_VALUE"""),"Análisis de resultados de simulaciones") -> Análisis de resultados de simulaciones
A38: Tipo de Recurso a utilizar | B38: Tipo | C38: Valor maximo recomendado en Minutos | D38: Tiempo Aproximado ( unicamente el valor de minutos ) | I38: Validacion
A39: Presentacion | B39: Obligatorio | C39: 30 | D39: 15 | I39: =IF(D39<=C39,"Correcto", "Corregir") -> Correcto
A40: Video | B40: Obligatorio | C40: 6 | D40: 5 | I40: =IF(D40<=C40,"Correcto", "Corregir") -> Correcto
A41: Lectura | B41: Optativo | C41: 10 | D41: 5 | I41: =IF(D41<=C41,"Correcto", "Corregir") -> Correcto
A42: Ejercicio Demostrativo | B42: Obligatorio | C42: 30 | D42: 30 | I42: =IF(D42<=C42,"Correcto", "Corregir") -> Correcto
A44: 3. Área de Habilidades (Saber Hacer) | G44: Tiempo Aproximado | H44: =B50 -> 30
G45: Tiene que estar en un rango de 30 a 50 minutos
A46: Actividad 1 (Obligatoria)
A47: Competencia que predomina en la actividad | B47: Analiza .. los principios basicos de la teoría de sistemas y su importancia en la vida mediante modelos sistémicos y recursos gráficos para analizar el funcionamiento, la estructura y las interacciones de los sistemas en distintos entornos tecnológicos
A48: Tipo de Actividad | B48: Analisis
A49: Ponderación | B49: 1
A50: Tiempo Aproximado | B50: 30
A51: Coloca el tiempo que usar en la actividad, un tiempo sugerido 30 minutos
A52: Descripcion de la Actividad
A53: Los estudiantes aplican la competencia Aplica y Analiza el modelo. 1. Se presenta un caso dinámico (ej. "La relación entre la publicidad y la calidad percibida"). 2. Los estudiantes deben Analizar el sistema para construir un DCC formal (incluyendo polaridades +/-, bucles R/C). 3. Aplicar la lógica de transición, identificando qué variables son Acumulaciones (Niveles) y cuáles son Tasas de Cambio (Flujos), preparando el terreno para la simulación en VENSIM.
A57: Actividad 2 (Optativa puedes hacerla si lo consideras apropiado)
A58: Competencia que predomina en la actividad
A59: Tipo de Actividad
A60: Ponderación
A61: Tiempo Aproximado
A62: Coloca el tiempo que usar en la actividad, un tiempo sugerido 20 minutos
A63: Descripcion de la Actividad
A68: 3. Cierre | G68: Tiempo Aproximado | H68: =B70 -> 10
G69: Tiene que estar en un rango de 10 a 15 minutos
A70: Tiempo Aproximado | B70: 10
A71: Asignacion de Actividades
A72: 1. Conclusión (5 min): El DCC es la herramienta principal de diagnóstico: nos permite ver cómo las Acumulaciones (Niveles) y las Tasas (Flujos) interactúan en el tiempo. La simulación convierte nuestro modelo conceptual en evidencia dinámica. 2. Asignación de Actividades (10 min): Tarea Preparatoria Obligatoria (para Semana 10): Investigar los 4-5 Arquetipos Sistémicos más comunes (ej. Límites al Crecimiento, Desplazamiento de la Carga, Soluciones que Fallan) y buscar un ejemplo de la vida real para cada uno. Estos arquetipos son la clave para la intervención sistémica. Tarea de Software (Opcional): Instalar VENSIM (o el software de simulación dinámico designado) y practicar la construcción de un DCC simple.
A74: Resuelve alguna duda, asigna las actividades que deben realizar, dudas de proyectos, etc

Sheet S.10
B2: Diseño de la Sesión de Laboratorio
B4: Curso | C4: ='Diseño'!C4 -> 722 - Teoría de Sistemas 1
B5: Semana | C5: 10
B6: Tiempo | C6: =H10+H21+H44+H68 -> 100
B7: Ponderación | C7: =B49+B60 -> 1
B8: Validación de Tiempo | C8: =IF(H44<=0, "❌ ERROR: La Actividad 1 debe tener un tiempo mayor a 0.", IF(H21>60, "❌ ERROR: El 'Área de Conocimiento' no puede exceder los 60 min.", IF((H10+H21+H44)<100, "❌ ERROR: El tiempo total debe ser de al menos 100 min.", "✅ VALIDACIÓN CORRECTA"))) -> ❌ ERROR: El tiempo total debe ser de al menos 100 min.
A10: 1. Área Actitudinal (Saber Ser) | G10: Tiempo Aproximado | H10: =B13 -> 5
G11: Tiene que estar en un rango de 3 a 5 minutos
A12: Nombre del Valor | B12: Experimentación
A13: Tiempo Aproximado | B13: 5
A14: Descripcion
A15: Disposición a probar diferentes escenarios (políticas de intervención) en un entorno simulado para predecir su impacto real.
A17: Como se relaciona con los conocimientos de la sesion y se aplicaria
A18: Se relaciona con la Simulación con VENSIM y el Análisis de Impacto. Fomenta que el estudiante Aplique la herramienta para pasar de la descripción a la predicción del comportamiento del sistema, validando la lógica del modelo.
A21: 2. Área Conocimiento (Saber) | G21: Tiempo Aproximado | H21: =SUM(D39:H42) -> 55
G22: No puede exceder los 60 minutos
A23: Competencia a desarrollar | B23: Analiza .. los principios basicos de la teoría de sistemas y su importancia en la vida mediante modelos sistémicos y recursos gráficos para analizar el funcionamiento, la estructura y las interacciones de los sistemas en distintos entornos tecnológicos
A24: Competencia a desarrollar
A26: 2.1 Contenido
A27: No. | B27: Unidad | D27: Tema | F27: Sub Tema
A28: 1 | B28: =IFERROR(__xludf.DUMMYFUNCTION("FILTER('Diseño'!D:D,'Diseño'!H:H=$C$5)"),"Unidad 4: Modelación y simulación dinámica de sistemas") -> Unidad 4: Modelación y simulación dinámica de sistemas | D28: =IFERROR(__xludf.DUMMYFUNCTION("FILTER('Diseño'!E:E,'Diseño'!H:H=$C$5)"),"Simulación con VENSIM") -> Simulación con VENSIM | F28: =IFERROR(__xludf.DUMMYFUNCTION("FILTER('Diseño'!F:F,'Diseño'!H:H=$C$5)"),"Simulación de sistemas complejos") -> Simulación de sistemas complejos
A29: 2 | B29: =IFERROR(__xludf.DUMMYFUNCTION("""COMPUTED_VALUE"""),"Unidad 4: Modelación y simulación dinámica de sistemas") -> Unidad 4: Modelación y simulación dinámica de sistemas | D29: =IFERROR(__xludf.DUMMYFUNCTION("""COMPUTED_VALUE"""),"Simulación con VENSIM") -> Simulación con VENSIM | F29: =IFERROR(__xludf.DUMMYFUNCTION("""COMPUTED_VALUE"""),"Impacto de los cambios en variables") -> Impacto de los cambios en variables
A30: 3 | B30: =IFERROR(__xludf.DUMMYFUNCTION("""COMPUTED_VALUE"""),"Unidad 4: Modelación y simulación dinámica de sistemas") -> Unidad 4: Modelación y simulación dinámica de sistemas | D30: =IFERROR(__xludf.DUMMYFUNCTION("""COMPUTED_VALUE"""),"Simulación con VENSIM") -> Simulación con VENSIM | F30: =IFERROR(__xludf.DUMMYFUNCTION("""COMPUTED_VALUE"""),"Integración de VENSIM en la toma de decisiones") -> Integración de VENSIM en la toma de decisiones
A31: 4 | B31: =IFERROR(__xludf.DUMMYFUNCTION("""COMPUTED_VALUE"""),"Unidad 4: Modelación y simulación dinámica de sistemas") -> Unidad 4: Modelación y simulación dinámica de sistemas | D31: =IFERROR(__xludf.DUMMYFUNCTION("""COMPUTED_VALUE"""),"Simulación con VENSIM") -> Simulación con VENSIM | F31: =IFERROR(__xludf.DUMMYFUNCTION("""COMPUTED_VALUE"""),"Ejemplos prácticos con simulaciones") -> Ejemplos prácticos con simulaciones
A32: 5 | B32: =IFERROR(__xludf.DUMMYFUNCTION("""COMPUTED_VALUE"""),"Unidad 5: Toma de decisiones sistémicas") -> Unidad 5: Toma de decisiones sistémicas | D32: =IFERROR(__xludf.DUMMYFUNCTION("""COMPUTED_VALUE"""),"Patrones y tendencias en sistemas") -> Patrones y tendencias en sistemas | F32: =IFERROR(__xludf.DUMMYFUNCTION("""COMPUTED_VALUE"""),"Identificación de patrones sistémicos") -> Identificación de patrones sistémicos
A33: 6 | B33: =IFERROR(__xludf.DUMMYFUNCTION("""COMPUTED_VALUE"""),"Unidad 5: Toma de decisiones sistémicas") -> Unidad 5: Toma de decisiones sistémicas | D33: =IFERROR(__xludf.DUMMYFUNCTION("""COMPUTED_VALUE"""),"Patrones y tendencias en sistemas") -> Patrones y tendencias en sistemas | F33: =IFERROR(__xludf.DUMMYFUNCTION("""COMPUTED_VALUE"""),"Ejemplos de patrones y tendencias en sistemas") -> Ejemplos de patrones y tendencias en sistemas
A34: 7 | B34: =IFERROR(__xludf.DUMMYFUNCTION("""COMPUTED_VALUE"""),"Unidad 5: Toma de decisiones sistémicas") -> Unidad 5: Toma de decisiones sistémicas | D34: =IFERROR(__xludf.DUMMYFUNCTION("""COMPUTED_VALUE"""),"Patrones y tendencias en sistemas") -> Patrones y tendencias en sistemas | F34: =IFERROR(__xludf.DUMMYFUNCTION("""COMPUTED_VALUE"""),"Predicción de comportamientos en sistemas") -> Predicción de comportamientos en sistemas
B35: =IFERROR(__xludf.DUMMYFUNCTION("""COMPUTED_VALUE"""),"Unidad 5: Toma de decisiones sistémicas") -> Unidad 5: Toma de decisiones sistémicas | D35: =IFERROR(__xludf.DUMMYFUNCTION("""COMPUTED_VALUE"""),"Patrones y tendencias en sistemas") -> Patrones y tendencias en sistemas | F35: =IFERROR(__xludf.DUMMYFUNCTION("""COMPUTED_VALUE"""),"Impacto de patrones en toma de decisiones") -> Impacto de patrones en toma de decisiones
A36: 2.2 Recursos Educativos
A38: Tipo de Recurso a utilizar | B38: Tipo | C38: Valor maximo recomendado en Minutos | D38: Tiempo Aproximado ( unicamente el valor de minutos ) | I38: Validacion
A39: Presentacion | B39: Obligatorio | C39: 30 | D39: 15 | I39: =IF(D39<=C39,"Correcto", "Corregir") -> Correcto
A40: Video | B40: Obligatorio | C40: 6 | D40: 5 | I40: =IF(D40<=C40,"Correcto", "Corregir") -> Correcto
A41: Lectura | B41: Optativo | C41: 10 | D41: 5 | I41: =IF(D41<=C41,"Correcto", "Corregir") -> Correcto
A42: Ejercicio Demostrativo | B42: Obligatorio | C42: 30 | D42: 30 | I42: =IF(D42<=C42,"Correcto", "Corregir") -> Correcto
A44: 3. Área de Habilidades (Saber Hacer) | G44: Tiempo Aproximado | H44: =B50 -> 30
G45: Tiene que estar en un rango de 30 a 50 minutos
A46: Actividad 1 (Obligatoria)
A47: Competencia que predomina en la actividad | B47: Analiza .. los principios basicos de la teoría de sistemas y su importancia en la vida mediante modelos sistémicos y recursos gráficos para analizar el funcionamiento, la estructura y las interacciones de los sistemas en distintos entornos tecnológicos
A48: Tipo de Actividad | B48: Ejercicio practico
A49: Ponderación | B49: 1
A50: Tiempo Aproximado | B50: 30
A51: Coloca el tiempo que usar en la actividad, un tiempo sugerido 30 minutos
A52: Descripcion de la Actividad
A53: Los estudiantes Aplican y Analizan un modelo DCC simple previamente construido (ej. "Crecimiento de un producto"). 1. Construir y simular el modelo en VENSIM. 2. Analizar el patrón de comportamiento (BOT) generado por la simulación. 3. Experimentar con una variable (ej. reducir el tiempo de retraso) y analizar el nuevo impacto. 4. Identificar si el patrón de comportamiento corresponde a un Arquetipo Sistémico conocido (ej. el sistema solo crece y colapsa: Límites al Crecimiento).
A57: Actividad 2 (Optativa puedes hacerla si lo consideras apropiado)
A58: Competencia que predomina en la actividad
A59: Tipo de Actividad
A60: Ponderación
A61: Tiempo Aproximado
A62: Coloca el tiempo que usar en la actividad, un tiempo sugerido 20 minutos
A63: Descripcion de la Actividad
A68: 3. Cierre | G68: Tiempo Aproximado | H68: =B70 -> 10
G69: Tiene que estar en un rango de 10 a 15 minutos
A70: Tiempo Aproximado | B70: 10
A71: Asignacion de Actividades
A72: 1. Conclusión (5 min): La simulación nos permite ir más allá del DCC estático, viendo el comportamiento temporal. Los Arquetipos son atajos mentales para identificar las estructuras comunes que causan los problemas recurrentes. 2. Asignación de Actividades (10 min): Tarea Preparatoria Obligatoria (para Semana 11): Estudiar a fondo los Arquetipos Sistémicos. Preparar un breve análisis de un Arquetipo (ej. Desplazamiento de la Carga), identificando su estructura de DCC y un caso real donde se aplica. Tarea de Refuerzo: Repasar los hábitos del pensador sistémico y cómo se aplican al analizar un resultado de simulación. examen final para la semana 11
A74: Resuelve alguna duda, asigna las actividades que deben realizar, dudas de proyectos, etc

Sheet S.11
B2: Diseño de la Sesión de Laboratorio
B4: Curso | C4: ='Diseño'!C4 -> 722 - Teoría de Sistemas 1
B5: Semana | C5: 11
B6: Tiempo | C6: =H10+H21+H44+H68 -> 100
B7: Ponderación | C7: =B49+B60 -> 1
B8: Validación de Tiempo | C8: =IF(H44<=0, "❌ ERROR: La Actividad 1 debe tener un tiempo mayor a 0.", IF(H21>60, "❌ ERROR: El 'Área de Conocimiento' no puede exceder los 60 min.", IF((H10+H21+H44)<100, "❌ ERROR: El tiempo total debe ser de al menos 100 min.", "✅ VALIDACIÓN CORRECTA"))) -> ❌ ERROR: El tiempo total debe ser de al menos 100 min.
A10: 1. Área Actitudinal (Saber Ser) | G10: Tiempo Aproximado | H10: =B13 -> 5
G11: Tiene que estar en un rango de 3 a 5 minutos
A12: Nombre del Valor | B12: Visión Estratégica
A13: Tiempo Aproximado | B13: 5
A14: Descripcion
A15: Capacidad de identificar los puntos de máximo apalancamiento (lugares donde una pequeña acción genera un gran cambio) dentro de un sistema complejo.
A17: Como se relaciona con los conocimientos de la sesion y se aplicaria
A18: Se relaciona con los Arquetipos y la Resolución de Problemas Sistémicos. Fomenta que el estudiante busque soluciones a nivel de estructura (alto apalancamiento), en lugar de soluciones a nivel de eventos (bajo apalancamiento).
A21: 2. Área Conocimiento (Saber) | G21: Tiempo Aproximado | H21: =SUM(D39:H42) -> 55
G22: No puede exceder los 60 minutos
A23: Competencia a desarrollar | B23: emplea los principios básicos de la teoría general de sistemas y del enfoque sistémico el desarrollo de simulaciones dinámicas y la práctica constante de hábitos de pensamiento sistémico para formular soluciones a problemas de baja y media complejidad
A24: Competencia a desarrollar
A26: 2.1 Contenido
A27: No. | B27: Unidad | D27: Tema | F27: Sub Tema
A28: 1 | B28: =IFERROR(__xludf.DUMMYFUNCTION("FILTER('Diseño'!D:D,'Diseño'!H:H=$C$5)"),"Unidad 5: Toma de decisiones sistémicas") -> Unidad 5: Toma de decisiones sistémicas | D28: =IFERROR(__xludf.DUMMYFUNCTION("FILTER('Diseño'!E:E,'Diseño'!H:H=$C$5)"),"Patrones y tendencias en sistemas") -> Patrones y tendencias en sistemas | F28: =IFERROR(__xludf.DUMMYFUNCTION("FILTER('Diseño'!F:F,'Diseño'!H:H=$C$5)"),"Ejemplos de arquetipos sistémicos comunes") -> Ejemplos de arquetipos sistémicos comunes
A29: 2 | B29: =IFERROR(__xludf.DUMMYFUNCTION("""COMPUTED_VALUE"""),"Unidad 5: Toma de decisiones sistémicas") -> Unidad 5: Toma de decisiones sistémicas | D29: =IFERROR(__xludf.DUMMYFUNCTION("""COMPUTED_VALUE"""),"Patrones y tendencias en sistemas") -> Patrones y tendencias en sistemas | F29: =IFERROR(__xludf.DUMMYFUNCTION("""COMPUTED_VALUE"""),"Arquetipos y resolución de problemas sistémicos") -> Arquetipos y resolución de problemas sistémicos
A30: 3 | B30: =IFERROR(__xludf.DUMMYFUNCTION("""COMPUTED_VALUE"""),"Unidad 5: Toma de decisiones sistémicas") -> Unidad 5: Toma de decisiones sistémicas | D30: =IFERROR(__xludf.DUMMYFUNCTION("""COMPUTED_VALUE"""),"Toma de decisiones sistémicas") -> Toma de decisiones sistémicas | F30: =IFERROR(__xludf.DUMMYFUNCTION("""COMPUTED_VALUE"""),"Uso de VENSIM para la toma de decisiones") -> Uso de VENSIM para la toma de decisiones
A31: 4 | B31: =IFERROR(__xludf.DUMMYFUNCTION("""COMPUTED_VALUE"""),"Unidad 5: Toma de decisiones sistémicas") -> Unidad 5: Toma de decisiones sistémicas | D31: =IFERROR(__xludf.DUMMYFUNCTION("""COMPUTED_VALUE"""),"Toma de decisiones sistémicas") -> Toma de decisiones sistémicas | F31: =IFERROR(__xludf.DUMMYFUNCTION("""COMPUTED_VALUE"""),"Desarrollo de estrategias de toma de decisiones") -> Desarrollo de estrategias de toma de decisiones
A32: 5 | B32: =IFERROR(__xludf.DUMMYFUNCTION("""COMPUTED_VALUE"""),"Unidad 5: Toma de decisiones sistémicas") -> Unidad 5: Toma de decisiones sistémicas | D32: =IFERROR(__xludf.DUMMYFUNCTION("""COMPUTED_VALUE"""),"Toma de decisiones sistémicas") -> Toma de decisiones sistémicas | F32: =IFERROR(__xludf.DUMMYFUNCTION("""COMPUTED_VALUE"""),"Análisis de ejemplos reales") -> Análisis de ejemplos reales
A33: 6 | B33: =IFERROR(__xludf.DUMMYFUNCTION("""COMPUTED_VALUE"""),"Unidad 5: Toma de decisiones sistémicas") -> Unidad 5: Toma de decisiones sistémicas | D33: =IFERROR(__xludf.DUMMYFUNCTION("""COMPUTED_VALUE"""),"Toma de decisiones sistémicas") -> Toma de decisiones sistémicas | F33: =IFERROR(__xludf.DUMMYFUNCTION("""COMPUTED_VALUE"""),"Hábitos para análisis de información sistémica") -> Hábitos para análisis de información sistémica
A34: 7 | B34: =IFERROR(__xludf.DUMMYFUNCTION("""COMPUTED_VALUE"""),"Unidad 5: Toma de decisiones sistémicas") -> Unidad 5: Toma de decisiones sistémicas | D34: =IFERROR(__xludf.DUMMYFUNCTION("""COMPUTED_VALUE"""),"Toma de decisiones sistémicas") -> Toma de decisiones sistémicas | F34: =IFERROR(__xludf.DUMMYFUNCTION("""COMPUTED_VALUE"""),"Resolución de problemas con enfoque sistémico") -> Resolución de problemas con enfoque sistémico
B35: =IFERROR(__xludf.DUMMYFUNCTION("""COMPUTED_VALUE"""),"Unidad 5: Toma de decisiones sistémicas") -> Unidad 5: Toma de decisiones sistémicas | D35: =IFERROR(__xludf.DUMMYFUNCTION("""COMPUTED_VALUE"""),"Toma de decisiones sistémicas") -> Toma de decisiones sistémicas | F35: =IFERROR(__xludf.DUMMYFUNCTION("""COMPUTED_VALUE"""),"Impacto de la retroalimentación en decisiones") -> Impacto de la retroalimentación en decisiones
A36: 2.2 Recursos Educativos
A38: Tipo de Recurso a utilizar | B38: Tipo | C38: Valor maximo recomendado en Minutos | D38: Tiempo Aproximado ( unicamente el valor de minutos ) | I38: Validacion
A39: Presentacion | B39: Obligatorio | C39: 30 | D39: 15 | I39: =IF(D39<=C39,"Correcto", "Corregir") -> Correcto
A40: Video | B40: Obligatorio | C40: 6 | D40: 5 | I40: =IF(D40<=C40,"Correcto", "Corregir") -> Correcto
A41: Lectura | B41: Optativo | C41: 10 | D41: 5 | I41: =IF(D41<=C41,"Correcto", "Corregir") -> Correcto
A42: Ejercicio Demostrativo | B42: Obligatorio | C42: 30 | D42: 30 | I42: =IF(D42<=C42,"Correcto", "Corregir") -> Correcto
A44: 3. Área de Habilidades (Saber Hacer) | G44: Tiempo Aproximado | H44: =B50 -> 30
G45: Tiene que estar en un rango de 30 a 50 minutos
A46: Actividad 1 (Obligatoria)
A47: Competencia que predomina en la actividad | B47: emplea los principios básicos de la teoría general de sistemas y del enfoque sistémico el desarrollo de simulaciones dinámicas y la práctica constante de hábitos de pensamiento sistémico para formular soluciones a problemas de baja y media complejidad
A48: Tipo de Actividad | B48: otros
A49: Ponderación | B49: 1
A50: Tiempo Aproximado | B50: 30
A51: Coloca el tiempo que usar en la actividad, un tiempo sugerido 30 minutos
A52: Descripcion de la Actividad
A57: Actividad 2 (Optativa puedes hacerla si lo consideras apropiado)
A58: Competencia que predomina en la actividad
A59: Tipo de Actividad
A60: Ponderación
A61: Tiempo Aproximado
A62: Coloca el tiempo que usar en la actividad, un tiempo sugerido 20 minutos
A63: Descripcion de la Actividad
A68: 3. Cierre | G68: Tiempo Aproximado | H68: =B70 -> 10
G69: Tiene que estar en un rango de 10 a 15 minutos
A70: Tiempo Aproximado | B70: 10
A71: Asignacion de Actividades
A72: 1. Conclusión (5 min): La meta del pensamiento sistémico es cambiar el sistema, no solo gestionar los síntomas. El uso de Arquetipos y Simulación permite una Toma de Decisiones Estratégica y proactiva.
A74: Resuelve alguna duda, asigna las actividades que deben realizar, dudas de proyectos, etc

Sheet Proyectos
B2: Proyectos
B4: Curso | C4: ='Diseño'!C4 -> 722 - Teoría de Sistemas 1
B5: Tiempo | C5: =H9+H26+H43 -> 10
B6: Ponderación | C6: =F9+F26+F43 -> 60
B7: La sumatoria de los puntos de los proyectos debe superar el 60% del total de la nota, no puede ser un 100%
A9: 1. Primer Proyecto | E9: Ponderación | F9: 60 | G9: Horas para realizarlo | H9: 10
A10: Obligatorio
A11: Competencia a desarrollar | B11: identifica los conceptos fundamentales de la teoría de sistemas y del pensamiento sistémico mediante la revisión de definiciones para reconocer los elementos esenciales en el análisis y modelación de sistemas
A12: Competencia a desarrollar | B12: Refina un problema de ingeniería o un sistema complejo mediante el uso de Diagramas de Ciclos Causales, Mapas DSRP y metodologías de modelación sistémica para identificar relaciones causales, retroalimentaciones y estructuras subyacentes que permitan mejorar su comprensión y gestión.
A13: Competencia a desarrollar | B13: comprende los fundamentos conceptuales del pensamiento sistémico y la naturaleza de los sistemas de la realidad a través del estudio de teorías, modelos mentales y estructuras de retroalimentación para distinguir los sistemas naturales, físicos diseñados, abstractos diseñados y de actividad humana
A14: Titulo | B14: De la Ceguera al Análisis: Mapeo de la Escalera de Inferencias y el Iceberg
A15: Qué tecnologías, lenguajes de programación, plataformas, hardware o software se utilizaran
A16: powerPoint,keynote o herramientas de mapeo como plectica o draw.io
A19: Descripción de lo que se realizara
A20: Seleccionar un conflicto o problema recurrente (personal, laboral o de gestión simple) y analizarlo en profundidad: 1. Mapear la Escalera de Inferencias del actor principal, identificando sus supuestos ocultos (Modelos Mentales). 2. Aplicar el Modelo del Iceberg para demostrar que la solución enfocada en el Evento falla, y proponer un punto de Intervención Estructural. 3. Clasificar el sistema elegido (natural, diseñado, actividad humana) y justificar la presencia de emergencia o sinergia.
A26: 2. Segundo Proyecto | E26: Ponderación | G26: Horas para realizarlo
A27: Obligatorio
A28: Competencia a desarrollar
A29: Competencia a desarrollar
A30: Competencia a desarrollar
A31: Titulo
A32: Qué tecnologías, lenguajes de programación, plataformas, hardware o software se utilizaran
A36: Descripción de lo que se realizara
A43: 3. Tercer Proyecto | E43: Ponderación | G43: Horas para realizarlo
A44: Optativa
A45: Competencia a desarrollar
A46: Competencia a desarrollar
A47: Competencia a desarrollar
A48: Titulo
A49: Qué tecnologías, lenguajes de programación, plataformas, hardware o software se utilizaran
A53: Descripción de lo que se realizara

Sheet Practicas
B2: Practicas
B4: Curso | C4: ='Diseño'!C4 -> 722 - Teoría de Sistemas 1
B5: Tiempo | C5: =H9+H26+H43+H60+H77+H94+H111 -> 8
B6: Ponderación | C6: =F9+F26+F43+F60+F77+F94+F111 -> 20
B7: La sumatoria de los puntos de los practicas debe no debe super el 20%
A9: 1. Primera Practica | E9: Ponderación | F9: 20 | G9: Horas para realizarlo | H9: 8
A10: Obligatoria
A11: Competencia a desarrollar | B11: identifica los conceptos fundamentales de la teoría de sistemas y del pensamiento sistémico mediante la revisión de definiciones para reconocer los elementos esenciales en el análisis y modelación de sistemas
A12: Competencia a desarrollar | B12: comprende los fundamentos conceptuales del pensamiento sistémico y la naturaleza de los sistemas de la realidad a través del estudio de teorías, modelos mentales y estructuras de retroalimentación para distinguir los sistemas naturales, físicos diseñados, abstractos diseñados y de actividad humana
A13: Competencia a desarrollar | B13: Analiza .. los principios basicos de la teoría de sistemas y su importancia en la vida mediante modelos sistémicos y recursos gráficos para analizar el funcionamiento, la estructura y las interacciones de los sistemas en distintos entornos tecnológicos
A14: Titulo | B14: Mapeo de la Dinámica Oculta: Identificación de la Retroalimentación
A15: Qué tecnologías, lenguajes de programación, plataformas, hardware o software se utilizaran
A16: Herramienta de diagramación simple (ej. Miro, Google Drawings, PowerPoint/Keynote, draw.io, plectica etc)
A19: Descripción de lo que se realizara
A20: Seleccionar dos escenarios o situaciones de complejidad baja (uno que muestre crecimiento/declive acelerado y otro que muestre equilibrio/estabilización, ej. un rumor, un aumento salarial, un plan de dieta, o el ciclo de mantenimiento de equipos). 1. Para el Escenario 1 (Refuerzo), identificar 4-5 variables clave y dibujar un Bucle de Refuerzo (R) con las polaridades correctas (+/−). 2. Para el Escenario 2 (Compensación), identificar 4-5 variables y dibujar un Bucle de Compensación (C) con las polaridades correctas. 3. Analizar cómo la dinámica del bucle genera el patrón de comportamiento (crecimiento exponencial vs. estabilización) y proponer una acción que no rompa el bucle, sino que lo modifique estratégicamente.
A26: 2. Segunda Practica | E26: Ponderación | G26: Horas para realizarlo
A27: Optativa
A28: Competencia a desarrollar
A29: Competencia a desarrollar
A30: Competencia a desarrollar
A31: Titulo
A32: Qué tecnologías, lenguajes de programación, plataformas, hardware o software se utilizaran
A36: Descripción de lo que se realizara
A43: 3. Tercera Practica | E43: Ponderación | G43: Horas para realizarlo
A44: Optativa
A45: Competencia a desarrollar
A46: Competencia a desarrollar
A47: Competencia a desarrollar
A48: Titulo
A49: Qué tecnologías, lenguajes de programación, plataformas, hardware o software se utilizaran
A53: Descripción de lo que se realizara
A60: 4. Cuarta Practica | E60: Ponderación | G60: Horas para realizarlo
A61: Optativa
A62: Competencia a desarrollar
A63: Competencia a desarrollar
A64: Competencia a desarrollar
A65: Titulo
A66: Qué tecnologías, lenguajes de programación, plataformas, hardware o software se utilizaran
A70: Descripción de lo que se realizara
A77: 5. Quinta Practica | E77: Ponderación | G77: Horas para realizarlo
A78: Optativa
A79: Competencia a desarrollar
A80: Competencia a desarrollar
A81: Competencia a desarrollar
A82: Titulo
A83: Qué tecnologías, lenguajes de programación, plataformas, hardware o software se utilizaran
A87: Descripción de lo que se realizara
A94: 6. Sexta Practica | E94: Ponderación | G94: Horas para realizarlo
A95: Optativa
A96: Competencia a desarrollar
A97: Competencia a desarrollar
A98: Competencia a desarrollar
A99: Titulo
A100: Qué tecnologías, lenguajes de programación, plataformas, hardware o software se utilizaran
A104: Descripción de lo que se realizara
A111: 7. Septima Practica | E111: Ponderación | G111: Horas para realizarlo
A112: Optativa
A113: Competencia a desarrollar
A114: Competencia a desarrollar
A115: Competencia a desarrollar
A116: Titulo
A117: Qué tecnologías, lenguajes de programación, plataformas, hardware o software se utilizaran
A121: Descripción de lo que se realizara

Sheet Tareas
B2: Tareas
B4: Curso | C4: ='Diseño'!C4 -> 722 - Teoría de Sistemas 1
B5: Tiempo | C5: =H9+H26+H43+H60+H77+H94+H111+H128 -> 14
B6: Ponderación | C6: =F9+F26+F43+F60+F77+F94+F111+F128 -> 10
B7: La sumatoria de los puntos de los practicas debe no debe super el 10% de la nota
A9: Tarea de fortalecimiento académico | E9: Ponderación | F9: 1 | G9: Horas para realizarlo | H9: 1
A10: Obligatoria se debe dejar en la sesion de diagnistico
A11: Competencia a desarrollar | B11: identifica los conceptos fundamentales de la teoría de sistemas y del pensamiento sistémico mediante la revisión de definiciones para reconocer los elementos esenciales en el análisis y modelación de sistemas
A12: Competencia a desarrollar | B12: comprende los fundamentos conceptuales del pensamiento sistémico y la naturaleza de los sistemas de la realidad a través del estudio de teorías, modelos mentales y estructuras de retroalimentación para distinguir los sistemas naturales, físicos diseñados, abstractos diseñados y de actividad humana
A13: Competencia a desarrollar
A14: Titulo | B14: Desconstrucción y Clasificación Sistémica
A15: Qué tecnologías, lenguajes de programación, plataformas, hardware o software se utilizaran
A16: Lucidchart, Miro o Draw.io (para diagramación de estructuras).
A19: Que conocimientos base y competencias esenciales se deben reforzar que permitan al estudiante afrontar con mayor solidez los contenidos del curso
A20: Antes de iniciar, el estudiante debe revisar: Concepto de Entropía y Neguentropía. Recursividad y Sinergia. Diferencia entre Causalidad Lineal y Causalidad Circular.
A26: 1. Primera Tarea | E26: Ponderación | F26: 1 | G26: Horas para realizarlo | H26: 1
A27: Obligatoria
A28: Competencia a desarrollar | B28: identifica los conceptos fundamentales de la teoría de sistemas y del pensamiento sistémico mediante la revisión de definiciones para reconocer los elementos esenciales en el análisis y modelación de sistemas
A29: Competencia a desarrollar | B29: comprende los fundamentos conceptuales del pensamiento sistémico y la naturaleza de los sistemas de la realidad a través del estudio de teorías, modelos mentales y estructuras de retroalimentación para distinguir los sistemas naturales, físicos diseñados, abstractos diseñados y de actividad humana
A30: Competencia a desarrollar
A31: Titulo
A32: Qué tecnologías, lenguajes de programación, plataformas, hardware o software se utilizaran
A33: Procesador de texto (Word, Google Docs) para el resumen de la investigación.
A36: Descripción de lo que se realizara
A37: Investigar a fondo las Operaciones Mentales Básicas del Pensamiento Sistémico (Distinción, Relación, Perspectiva, Organización) y la definición de Pensamiento Adaptativo Complejo. El estudiante debe resumir la esencia de cada operación y su rol en la construcción de modelos mentales sistémicos.
A43: 2. Segunda Tarea | E43: Ponderación | F43: 1 | G43: Horas para realizarlo | H43: 2
A44: Obligatoria
A45: Competencia a desarrollar | B45: comprende los fundamentos conceptuales del pensamiento sistémico y la naturaleza de los sistemas de la realidad a través del estudio de teorías, modelos mentales y estructuras de retroalimentación para distinguir los sistemas naturales, físicos diseñados, abstractos diseñados y de actividad humana
A46: Competencia a desarrollar | B46: identifica los conceptos fundamentales de la teoría de sistemas y del pensamiento sistémico mediante la revisión de definiciones para reconocer los elementos esenciales en el análisis y modelación de sistemas
A47: Competencia a desarrollar | B47: Analiza .. los principios basicos de la teoría de sistemas y su importancia en la vida mediante modelos sistémicos y recursos gráficos para analizar el funcionamiento, la estructura y las interacciones de los sistemas en distintos entornos tecnológicos
A48: Titulo
A49: Qué tecnologías, lenguajes de programación, plataformas, hardware o software se utilizaran
A50: Herramienta de diagramación simple (papel, PowerPoint, Miro) para los esquemas.
A53: Descripción de lo que se realizara
A54: Buscar tres ejemplos de situaciones (sociales o económicas) donde la causalidad lineal es una explicación insuficiente (ej. "castigar al culpable") y se requiere una explicación de causalidad circular (retroalimentación). Trazar un esquema muy simple (sin formalismos de DCC aún) para ilustrar el bucle.
A60: 3. Tercera Tarea | E60: Ponderación | F60: 1 | G60: Horas para realizarlo | H60: 2
A61: Optativa
A62: Competencia a desarrollar | B62: Analiza .. los principios basicos de la teoría de sistemas y su importancia en la vida mediante modelos sistémicos y recursos gráficos para analizar el funcionamiento, la estructura y las interacciones de los sistemas en distintos entornos tecnológicos
A63: Competencia a desarrollar | B63: comprende los fundamentos conceptuales del pensamiento sistémico y la naturaleza de los sistemas de la realidad a través del estudio de teorías, modelos mentales y estructuras de retroalimentación para distinguir los sistemas naturales, físicos diseñados, abstractos diseñados y de actividad humana
A64: Competencia a desarrollar | B64: identifica los conceptos fundamentales de la teoría de sistemas y del pensamiento sistémico mediante la revisión de definiciones para reconocer los elementos esenciales en el análisis y modelación de sistemas
A65: Titulo | B65: Definiciones formales de subsistemas
A66: Qué tecnologías, lenguajes de programación, plataformas, hardware o software se utilizaran
A67: Procesador de texto para las definiciones y los ejemplos.
A70: Descripción de lo que se realizara
A71: Investigar las definiciones formales de Subsistema, Suprasistema, Sinergia y Emergencia. Adicionalmente, buscar dos ejemplos de Sistemas Naturales y dos ejemplos de Sistemas Físicos Diseñados para practicar la clasificación que se verá en la próxima sesión.
A77: 4. Cuarta Tarea | E77: Ponderación | F77: 1 | G77: Horas para realizarlo | H77: 2
A78: Optativa
A79: Competencia a desarrollar | B79: identifica los conceptos fundamentales de la teoría de sistemas y del pensamiento sistémico mediante la revisión de definiciones para reconocer los elementos esenciales en el análisis y modelación de sistemas
A80: Competencia a desarrollar | B80: Analiza .. los principios basicos de la teoría de sistemas y su importancia en la vida mediante modelos sistémicos y recursos gráficos para analizar el funcionamiento, la estructura y las interacciones de los sistemas en distintos entornos tecnológicos
A81: Competencia a desarrollar
A82: Titulo | B82: Análisis de Problema Sistémico para Modelado Conceptual
A83: Qué tecnologías, lenguajes de programación, plataformas, hardware o software se utilizaran
A84: Procesador de texto o una simple hoja de cálculo.
A87: Descripción de lo que se realizara
A88: Elegir un problema sistémico de baja a media complejidad (ej. un problema de gestión de inventario, un conflicto social, un problema de tráfico recurrente). Listar al menos 6 variables clave que están interconectadas y que podrían formar la base de un Diagrama de Ciclos Causales (DCC).
A94: 5. Quinta Tarea | E94: Ponderación | F94: 1 | G94: Horas para realizarlo | H94: 2
A95: Optativa
A96: Competencia a desarrollar | B96: comprende los fundamentos conceptuales del pensamiento sistémico y la naturaleza de los sistemas de la realidad a través del estudio de teorías, modelos mentales y estructuras de retroalimentación para distinguir los sistemas naturales, físicos diseñados, abstractos diseñados y de actividad humana
A97: Competencia a desarrollar | B97: Analiza .. los principios basicos de la teoría de sistemas y su importancia en la vida mediante modelos sistémicos y recursos gráficos para analizar el funcionamiento, la estructura y las interacciones de los sistemas en distintos entornos tecnológicos
A98: Competencia a desarrollar | B98: emplea los principios básicos de la teoría general de sistemas y del enfoque sistémico el desarrollo de simulaciones dinámicas y la práctica constante de hábitos de pensamiento sistémico para formular soluciones a problemas de baja y media complejidad
A99: Titulo | B99: Aplicación del Modelo del Iceberg y Hábitos Sistémicos
A100: Qué tecnologías, lenguajes de programación, plataformas, hardware o software se utilizaran
A101: Procesador de texto para el reporte
A104: Descripción de lo que se realizara
A105: Elegir un problema personal o profesional. Aplicar el Modelo del Iceberg para identificar el Evento, los Patrones, la Estructura subyacente y el Modelo Mental que lo sostiene. Adicionalmente, investigar 3-5 Hábitos clave de un pensador sistémico y cómo la aplicación de uno de ellos podría haber evitado o resuelto el problema.
A111: 6. Sexta Tarea | E111: Ponderación | F111: 2 | G111: Horas para realizarlo | H111: 2
A112: Optativa
A113: Competencia a desarrollar | B113: Analiza .. los principios basicos de la teoría de sistemas y su importancia en la vida mediante modelos sistémicos y recursos gráficos para analizar el funcionamiento, la estructura y las interacciones de los sistemas en distintos entornos tecnológicos
A114: Competencia a desarrollar | B114: identifica los conceptos fundamentales de la teoría de sistemas y del pensamiento sistémico mediante la revisión de definiciones para reconocer los elementos esenciales en el análisis y modelación de sistemas
A115: Competencia a desarrollar
A116: Titulo | B116: Investigación de Mapas DSRP y Causalidad de Retroalimentación
A117: Qué tecnologías, lenguajes de programación, plataformas, hardware o software se utilizaran
A118: Procesador de texto o navegador web.
A121: Descripción de lo que se realizara
A122: Investigar los componentes principales de los Mapas DSRP (Distinciones, Sistemas, Relaciones, Perspectivas). Preparar un tutorial o resumen básico sobre la construcción de Diagramas de Causa y Efecto, enfocándose en cómo se utiliza la notación de las flechas para ilustrar la Retroalimentación (bucles).
A128: 7. Septima Tarea | E128: Ponderación | F128: 2 | G128: Horas para realizarlo | H128: 2
A129: Optativa
A130: Competencia a desarrollar | B130: Analiza .. los principios basicos de la teoría de sistemas y su importancia en la vida mediante modelos sistémicos y recursos gráficos para analizar el funcionamiento, la estructura y las interacciones de los sistemas en distintos entornos tecnológicos
A131: Competencia a desarrollar | B131: identifica los conceptos fundamentales de la teoría de sistemas y del pensamiento sistémico mediante la revisión de definiciones para reconocer los elementos esenciales en el análisis y modelación de sistemas
A132: Competencia a desarrollar | B132: comprende los fundamentos conceptuales del pensamiento sistémico y la naturaleza de los sistemas de la realidad a través del estudio de teorías, modelos mentales y estructuras de retroalimentación para distinguir los sistemas naturales, físicos diseñados, abstractos diseñados y de actividad humana
A133: Titulo | B133: Procesador de texto para el análisis.
A134: Qué tecnologías, lenguajes de programación, plataformas, hardware o software se utilizaran
A135: Procesador de texto para el análisis.
A138: Descripción de lo que se realizara
A139: Investigar los 4-5 Arquetipos Sistémicos más comunes (ej. Límites al Crecimiento, Desplazamiento de la Carga, Soluciones que Fallan). Para un solo Arquetipo (el elegido), el estudiante debe describir su estructura de DCC (conceptual) e identificar un ejemplo de la vida real donde se manifiesta.

Sheet Metadata
A1: Codigo-Nombre | B1: Competencias | C1: Competencias relacionadas al perfil del egresado (Especifica) | D1: Competencias relacionadas al perfil del egresado (General)
A2: 17 - Área Social Humanística 1 | B2: =Competencias!C13 -> Analiza .. los principios basicos de la teoría de sistemas y su importancia en la vida mediante modelos sistémicos y recursos gráficos para analizar el funcionamiento, la estructura y las interacciones de los sistemas en distintos entornos tecnológicos | C2: Aplica los conocimientos de su disciplina en la elaboración, fundamentación y defensa de argumentos para prevenir y resolver problemas complejos en su campo profesional, identificando y aplicando innovaciones. | D2: Aplica principios básicos de ingeniería, ciencias de computación y sistemas de información y comunicación, en la formulación y resolución adecuada de problemas complejos.
A3: 101 - Área Matemática Básica 1 | B3: =Competencias!C15 -> Refina un problema de ingeniería o un sistema complejo mediante el uso de Diagramas de Ciclos Causales, Mapas DSRP y metodologías de modelación sistémica para identificar relaciones causales, retroalimentaciones y estructuras subyacentes que permitan mejorar su comprensión y gestión. | C3: Identifica oportunidades y riesgos para la innovación y adaptación de conocimientos y tecnologías para resolver problemas. | D3: Aplica estándares de calidad, eficiencia y seguridad en la implementación adecuada de soluciones de software, hardware y TIC en general.
A4: 5 - Técnicas de Estudio e Investigación | B4: =Competencias!C17 -> emplea los principios básicos de la teoría general de sistemas y del enfoque sistémico el desarrollo de simulaciones dinámicas y la práctica constante de hábitos de pensamiento sistémico para formular soluciones a problemas de baja y media complejidad | C4: Demuestra pensamiento crítico, actitud investigativa y rigor analítico en el planteamiento y la resolución de problemas complejos. | D4: Aplica conocimientos tecnológicos con ética profesional y respetando y cuidando los recursos naturales, humanos y financieros.
A5: 39 - Deportes 1 | B5: =Competencias!C19 -> comprende los fundamentos conceptuales del pensamiento sistémico y la naturaleza de los sistemas de la realidad a través del estudio de teorías, modelos mentales y estructuras de retroalimentación para distinguir los sistemas naturales, físicos diseñados, abstractos diseñados y de actividad humana | C5: Toma decisiones profesionales con base en fundamentos teóricos, datos e información pertinente, válida y confiable. | D5: Maneja e Interpreta adecuadamente datos masivos, sean estos estructurados o no estructurados, facilitando su visualización e interpretación de forma eficaz en apoyo a la toma de decisiones.
A6: 6 - Idioma Tecnico 1 | B6: =Competencias!C21 -> identifica los conceptos fundamentales de la teoría de sistemas y del pensamiento sistémico mediante la revisión de definiciones para reconocer los elementos esenciales en el análisis y modelación de sistemas | C6: Demuestra destreza y habilidad en la selección, uso y adaptación de herramientas metodológicas, tecnológicas, equipos especializados y en la lectura e interpretación de datos, pertinentes al contexto de su ejercicio profesional. | D6: Domina diversos recursos de comunicación con el objetivo de presentar adecuadamente sus propuestas a variados tipos de audiencias, en idioma español, inglés e idealmente en un tercer idioma acorde a las necesidades globales.
A7: 19 - Área Social Humanística 2 | B7: =Competencias!C23 -> Diseña un controlador (ej. PID) o una estrategia de intervención sistémica para articular las herramientas de modelado y simulación para combinar las herramientas de modelado y simulación | C7: Identifica sus necesidades de actualización, capacitación y formación, durante su proceso formativo y en el ejercicio profesional, y busca los medios para cubrirlas por medios formales e informales, nacionales e internacionales, presenciales y en línea. | D7: Construye soluciones integrales trabajando en forma colaborativa y propositiva en equipos interdisciplinarios, en forma presencial o utilizando plataformas virtuales.
A8: 103 - Área Matemática Básica 2 | B8: =Competencias!C25 -> desarrolla pensamiento sistémico y la construcción de modelos mentales sistémicos con el fin de comprender, representar para comprender sistemas complejos en entornos dinámicos y multidisciplinarios | C8: Comunica a diversos públicos, información de su campo profesional, en varios lenguajes y formatos de manera asertiva, clara, rigurosa y precisa, con el uso apropiado de recursos tecnológicos. | D8: Actualiza permanente sus conocimientos relacionados con TIC en general, apoyándose en las estrategias de aprendizaje apropiadas.
A9: 960 - Matemática Para Computación 1 | C9: Se comunica correctamente en su lengua oficial y utiliza una lengua extranjera con el dominio requerido para el ejercicio de su profesión.
A10: 147 - Física Básica | C10: Lidera y colabora proactivamente en equipos de trabajo y en comunidades profesionales para el logro de objetivos y mejoramiento de la calidad de vida.
A11: 40 - Deportes 2
A12: 8 - Idioma Técnico 2
A13: 795 - Logica de Sitemas
A14: 962 - Matemática Para Computación 2
A15: 770 - Introducción a ala programación y computación 1
A16: 107 - Área Matemática Intermedia 1
A17: 150 - Fisica 1
A18: 1 - Ética Profesional
A19: 9 - Idioma Técnico 3
A20: 796 - Lenguajes Formales y de Programación
A21: 771 - Introducción a la Programación y Computación 2
A22: 112 - Área Matemática Intermedia 2
... A81: 0089 - Comunicación Asertiva
